{"devicePlatform":"","logFolder":"C:\\New-Bugzilla-Application\\New_Bugzilla-UI-V2\\Reports\\Edit_Product_Suite\\20190502_135602","runData":{"hostName":"Kumar.nagendra - HMECL001948.happiestminds.com","os":"Windows 10 64bit","katalonVersion":"5.3.0.1","browser":"Chrome 73.0.3683.103","hostAddress":"10.95.75.221","sessionId":"b5cea4eb3d8a97e5dd545d0562702045","seleniumVersion":"3.7.1","proxyInformation":"ProxyInformation{proxyOption\u003dNO_PROXY, proxyServerType\u003dHTTP, password\u003d, proxyServerAddress\u003d, proxyServerPort\u003d0}","platform":"Windows 10"},"type":"TEST_SUITE","name":"Edit_Product_Suite","id":"Test Suites/Edit_Product_Suite","source":"","message":"Test Cases/Edit_Product/version_section","description":"","startTime":1556785565124,"endTime":1556785668924,"childRecords":[{"isOptional":false,"type":"TEST_CASE","name":"Test Cases/Edit_Product/Edit_product_fields","id":"Test Cases/Edit_Product/Edit_product_fields","source":"C:\\\\New-Bugzilla-Application\\\\New_Bugzilla-UI-V2\\\\Test Cases\\\\Edit_Product\\\\Edit_product_fields.tc","message":"Test Cases/Edit_Product/Edit_product_fields","description":"","startTime":1556785565653,"endTime":1556785607396,"childRecords":[{"testStatus":{"stackTrace":"","statusValue":"INFO"},"type":"MESSAGE","name":"","message":"Evaluating variables for test case","startTime":1556785565704,"endTime":0,"childRecords":[],"interuppted":false},{"index":1,"isIgnoredIfFailed":false,"type":"TEST_STEP","name":"openBrowser","message":"Browser is opened with url: \u0027\u0027","description":"","startTime":1556785566176,"endTime":1556785569379,"childRecords":[{"testStatus":{"stackTrace":"","statusValue":"PASSED"},"type":"MESSAGE","name":"","message":"Browser is opened with url: \u0027\u0027","startTime":1556785569378,"endTime":0,"childRecords":[],"interuppted":false}],"interuppted":false},{"index":2,"isIgnoredIfFailed":false,"type":"TEST_STEP","name":"navigateToUrl","message":"Navigate to \u0027https://le-bugsui.staging.corp.arista.io/dashboard\u0027 successfully","description":"","startTime":1556785569380,"endTime":1556785583837,"childRecords":[{"testStatus":{"stackTrace":"","statusValue":"PASSED"},"type":"MESSAGE","name":"","message":"Navigate to \u0027https://le-bugsui.staging.corp.arista.io/dashboard\u0027 successfully","startTime":1556785583835,"endTime":0,"childRecords":[],"interuppted":false}],"interuppted":false},{"index":3,"isIgnoredIfFailed":false,"type":"TEST_STEP","name":"delay","message":"Delayed 3 second(s)","description":"","startTime":1556785583837,"endTime":1556785586881,"childRecords":[{"testStatus":{"stackTrace":"","statusValue":"PASSED"},"type":"MESSAGE","name":"","message":"Delayed 3 second(s)","startTime":1556785586881,"endTime":0,"childRecords":[],"interuppted":false}],"interuppted":false},{"index":4,"isIgnoredIfFailed":false,"type":"TEST_STEP","name":"reusable.loginBugZillaUI.login","message":"reusable.loginBugZillaUI.login is PASSED","description":"","startTime":1556785586883,"endTime":1556785587862,"childRecords":[{"testStatus":{"stackTrace":"","statusValue":"PASSED"},"type":"MESSAGE","name":"","message":"Current window maximized","startTime":1556785587038,"endTime":0,"childRecords":[],"interuppted":false},{"testStatus":{"stackTrace":"","statusValue":"PASSED"},"type":"MESSAGE","name":"","message":"Text \u0027knagendra-ext\u0027 is set on object \u0027Object Repository/Page_BugsUI/input_username\u0027","startTime":1556785587371,"endTime":0,"childRecords":[],"interuppted":false},{"testStatus":{"stackTrace":"","statusValue":"PASSED"},"type":"MESSAGE","name":"","message":"Text \u0027Kum1!@#$%^\u0026*()ar\u0027 is set on object \u0027Object Repository/Page_BugsUI/input_password\u0027","startTime":1556785587667,"endTime":0,"childRecords":[],"interuppted":false},{"testStatus":{"stackTrace":"","statusValue":"PASSED"},"type":"MESSAGE","name":"","message":"Object \u0027Object Repository/Page_BugsUI/button_Login\u0027 is clickable","startTime":1556785587732,"endTime":0,"childRecords":[],"interuppted":false},{"testStatus":{"stackTrace":"","statusValue":"PASSED"},"type":"MESSAGE","name":"","message":"Object: \u0027Object Repository/Page_BugsUI/button_Login\u0027 is clicked on","startTime":1556785587861,"endTime":0,"childRecords":[],"interuppted":false},{"testStatus":{"stackTrace":"","statusValue":"PASSED"},"type":"MESSAGE","name":"","message":"reusable.loginBugZillaUI.login is PASSED","startTime":1556785587862,"endTime":0,"childRecords":[],"interuppted":false}],"interuppted":false},{"index":5,"isIgnoredIfFailed":false,"type":"TEST_STEP","name":"delay","message":"Delayed 6 second(s)","description":"","startTime":1556785587863,"endTime":1556785593866,"childRecords":[{"testStatus":{"stackTrace":"","statusValue":"PASSED"},"type":"MESSAGE","name":"","message":"Delayed 6 second(s)","startTime":1556785593866,"endTime":0,"childRecords":[],"interuppted":false}],"interuppted":false},{"index":6,"isIgnoredIfFailed":false,"type":"TEST_STEP","name":"Statement - If (com.kms.katalon.core.webui.keyword.WebUiBuiltInKeywords.verifyElementPresent(com.kms.katalon.core.testobject.ObjectRepository.findTestObject(Page_BugsUI Dashboard/span_Dashboard), 0))","message":"Object: \u0027Object Repository/Page_BugsUI Dashboard/a_Edit\u0027 is clicked on","description":"","startTime":1556785593867,"endTime":1556785596193,"childRecords":[{"testStatus":{"stackTrace":"","statusValue":"WARNING"},"type":"MESSAGE","name":"","message":"Timeout \u00270\u0027 is invalid. Using default page load timeout: \u002730\u0027","startTime":1556785593890,"endTime":0,"childRecords":[],"interuppted":false},{"testStatus":{"stackTrace":"","statusValue":"PASSED"},"type":"MESSAGE","name":"","message":"Object \u0027Object Repository/Page_BugsUI Dashboard/span_Dashboard\u0027 is present","startTime":1556785593935,"endTime":0,"childRecords":[],"interuppted":false},{"index":1,"isIgnoredIfFailed":false,"type":"TEST_STEP","name":"Statement - If (com.kms.katalon.core.webui.keyword.WebUiBuiltInKeywords.verifyElementPresent(com.kms.katalon.core.testobject.ObjectRepository.findTestObject(Page_BugsUI Dashboard/button_Product), 10))","message":"Object: \u0027Object Repository/Page_BugsUI Dashboard/a_Edit\u0027 is clicked on","description":"","startTime":1556785593935,"endTime":1556785596193,"childRecords":[{"testStatus":{"stackTrace":"","statusValue":"PASSED"},"type":"MESSAGE","name":"","message":"Object \u0027Object Repository/Page_BugsUI Dashboard/button_Product\u0027 is present","startTime":1556785593967,"endTime":0,"childRecords":[],"interuppted":false},{"index":1,"isIgnoredIfFailed":false,"type":"TEST_STEP","name":"click","message":"Object: \u0027Object Repository/Page_BugsUI Dashboard/button_Product\u0027 is clicked on","description":"","startTime":1556785593967,"endTime":1556785594082,"childRecords":[{"testStatus":{"stackTrace":"","statusValue":"PASSED"},"type":"MESSAGE","name":"","message":"Object: \u0027Object Repository/Page_BugsUI Dashboard/button_Product\u0027 is clicked on","startTime":1556785594081,"endTime":0,"childRecords":[],"interuppted":false}],"interuppted":false},{"index":2,"isIgnoredIfFailed":false,"type":"TEST_STEP","name":"delay","message":"Delayed 2 second(s)","description":"","startTime":1556785594082,"endTime":1556785596084,"childRecords":[{"testStatus":{"stackTrace":"","statusValue":"PASSED"},"type":"MESSAGE","name":"","message":"Delayed 2 second(s)","startTime":1556785596084,"endTime":0,"childRecords":[],"interuppted":false}],"interuppted":false},{"index":3,"isIgnoredIfFailed":false,"type":"TEST_STEP","name":"Statement - If (com.kms.katalon.core.webui.keyword.WebUiBuiltInKeywords.verifyElementPresent(com.kms.katalon.core.testobject.ObjectRepository.findTestObject(Page_BugsUI Dashboard/a_Edit), 5))","message":"Object: \u0027Object Repository/Page_BugsUI Dashboard/a_Edit\u0027 is clicked on","description":"","startTime":1556785596085,"endTime":1556785596193,"childRecords":[{"testStatus":{"stackTrace":"","statusValue":"PASSED"},"type":"MESSAGE","name":"","message":"Object \u0027Object Repository/Page_BugsUI Dashboard/a_Edit\u0027 is present","startTime":1556785596109,"endTime":0,"childRecords":[],"interuppted":false},{"index":1,"isIgnoredIfFailed":false,"type":"TEST_STEP","name":"click","message":"Object: \u0027Object Repository/Page_BugsUI Dashboard/a_Edit\u0027 is clicked on","description":"","startTime":1556785596109,"endTime":1556785596192,"childRecords":[{"testStatus":{"stackTrace":"","statusValue":"PASSED"},"type":"MESSAGE","name":"","message":"Object: \u0027Object Repository/Page_BugsUI Dashboard/a_Edit\u0027 is clicked on","startTime":1556785596192,"endTime":0,"childRecords":[],"interuppted":false}],"interuppted":false}],"interuppted":false}],"interuppted":false}],"interuppted":false},{"index":7,"isIgnoredIfFailed":false,"type":"TEST_STEP","name":"verifyElementPresent","message":"Object \u0027Object Repository/Page_BugsUI Edit Product/span_Edit Product\u0027 is present","description":"","startTime":1556785596194,"endTime":1556785597836,"childRecords":[{"testStatus":{"stackTrace":"","statusValue":"WARNING"},"type":"MESSAGE","name":"","message":"Timeout \u00270\u0027 is invalid. Using default page load timeout: \u002730\u0027","startTime":1556785596199,"endTime":0,"childRecords":[],"interuppted":false},{"testStatus":{"stackTrace":"","statusValue":"PASSED"},"type":"MESSAGE","name":"","message":"Object \u0027Object Repository/Page_BugsUI Edit Product/span_Edit Product\u0027 is present","startTime":1556785597835,"endTime":0,"childRecords":[],"interuppted":false}],"interuppted":false},{"index":8,"isIgnoredIfFailed":false,"type":"TEST_STEP","name":"reusable.editPage.selectProduct","message":"reusable.editPage.selectProduct is PASSED","description":"","startTime":1556785597836,"endTime":1556785604812,"childRecords":[{"testStatus":{"stackTrace":"","statusValue":"PASSED"},"type":"MESSAGE","name":"","message":"Text \u0027Software\u0027 is set on object \u0027Object Repository/Page_BugsUI Edit Product/div_Choose Classification\u0027","startTime":1556785598268,"endTime":0,"childRecords":[],"interuppted":false},{"testStatus":{"stackTrace":"","statusValue":"PASSED"},"type":"MESSAGE","name":"","message":"Delayed 2 second(s)","startTime":1556785600271,"endTime":0,"childRecords":[],"interuppted":false},{"testStatus":{"stackTrace":"","statusValue":"PASSED"},"type":"MESSAGE","name":"","message":"Object: \u0027Object Repository/Page_BugsUI Edit Product/span_Software\u0027 is clicked on","startTime":1556785600384,"endTime":0,"childRecords":[],"interuppted":false},{"testStatus":{"stackTrace":"","statusValue":"PASSED"},"type":"MESSAGE","name":"","message":"Text \u00271-Auto-edit\u0027 is set on object \u0027Object Repository/Page_BugsUI Edit Product/div_Choose Product\u0027","startTime":1556785600678,"endTime":0,"childRecords":[],"interuppted":false},{"testStatus":{"stackTrace":"","statusValue":"PASSED"},"type":"MESSAGE","name":"","message":"Delayed 2 second(s)","startTime":1556785602680,"endTime":0,"childRecords":[],"interuppted":false},{"testStatus":{"stackTrace":"","statusValue":"PASSED"},"type":"MESSAGE","name":"","message":"Object: \u0027Object Repository/Page_BugsUI Edit Product/span_1-Auto-edit\u0027 is clicked on","startTime":1556785602810,"endTime":0,"childRecords":[],"interuppted":false},{"testStatus":{"stackTrace":"","statusValue":"PASSED"},"type":"MESSAGE","name":"","message":"Delayed 2 second(s)","startTime":1556785604811,"endTime":0,"childRecords":[],"interuppted":false},{"testStatus":{"stackTrace":"","statusValue":"PASSED"},"type":"MESSAGE","name":"","message":"reusable.editPage.selectProduct is PASSED","startTime":1556785604811,"endTime":0,"childRecords":[],"interuppted":false}],"interuppted":false},{"index":9,"isIgnoredIfFailed":false,"type":"TEST_STEP","name":"verifyElementPresent","message":"Object \u0027Object Repository/Page_BugsUI Edit Product/input_newName\u0027 is present","description":"","startTime":1556785604813,"endTime":1556785604839,"childRecords":[{"testStatus":{"stackTrace":"","statusValue":"WARNING"},"type":"MESSAGE","name":"","message":"Timeout \u00270\u0027 is invalid. Using default page load timeout: \u002730\u0027","startTime":1556785604814,"endTime":0,"childRecords":[],"interuppted":false},{"testStatus":{"stackTrace":"","statusValue":"PASSED"},"type":"MESSAGE","name":"","message":"Object \u0027Object Repository/Page_BugsUI Edit Product/input_newName\u0027 is present","startTime":1556785604826,"endTime":0,"childRecords":[],"interuppted":false}],"interuppted":false},{"index":10,"isIgnoredIfFailed":false,"type":"TEST_STEP","name":"verifyElementPresent","message":"Object \u0027Object Repository/Page_BugsUI Edit Product/textarea_description\u0027 is present","description":"","startTime":1556785604840,"endTime":1556785604868,"childRecords":[{"testStatus":{"stackTrace":"","statusValue":"WARNING"},"type":"MESSAGE","name":"","message":"Timeout \u00270\u0027 is invalid. Using default page load timeout: \u002730\u0027","startTime":1556785604841,"endTime":0,"childRecords":[],"interuppted":false},{"testStatus":{"stackTrace":"","statusValue":"PASSED"},"type":"MESSAGE","name":"","message":"Object \u0027Object Repository/Page_BugsUI Edit Product/textarea_description\u0027 is present","startTime":1556785604868,"endTime":0,"childRecords":[],"interuppted":false}],"interuppted":false},{"index":11,"isIgnoredIfFailed":false,"type":"TEST_STEP","name":"verifyElementPresent","message":"Object \u0027Object Repository/Page_BugsUI Edit Product/div_closed_for_bug_entry\u0027 is present","description":"","startTime":1556785604868,"endTime":1556785604903,"childRecords":[{"testStatus":{"stackTrace":"","statusValue":"WARNING"},"type":"MESSAGE","name":"","message":"Timeout \u00270\u0027 is invalid. Using default page load timeout: \u002730\u0027","startTime":1556785604879,"endTime":0,"childRecords":[],"interuppted":false},{"testStatus":{"stackTrace":"","statusValue":"PASSED"},"type":"MESSAGE","name":"","message":"Object \u0027Object Repository/Page_BugsUI Edit Product/div_closed_for_bug_entry\u0027 is present","startTime":1556785604903,"endTime":0,"childRecords":[],"interuppted":false}],"interuppted":false},{"index":12,"isIgnoredIfFailed":false,"type":"TEST_STEP","name":"Statement - If (com.kms.katalon.core.webui.keyword.WebUiBuiltInKeywords.verifyElementNotClickable(com.kms.katalon.core.testobject.ObjectRepository.findTestObject(Page_BugsUI Edit Product/button_update_product)))","description":"","startTime":1556785604903,"endTime":1556785605006,"childRecords":[{"testStatus":{"stackTrace":"","statusValue":"PASSED"},"type":"MESSAGE","name":"","message":"Object \u0027Object Repository/Page_BugsUI Edit Product/button_update_product\u0027 is NOT clickable","startTime":1556785605004,"endTime":0,"childRecords":[],"interuppted":false},{"index":1,"isIgnoredIfFailed":false,"type":"TEST_STEP","name":"Statement - assert true","description":"","startTime":1556785605004,"endTime":1556785605006,"childRecords":[],"interuppted":false}],"interuppted":false},{"index":14,"isIgnoredIfFailed":false,"type":"TEST_STEP","name":"scrollToElement","message":"Scroll to object \u0027Object Repository/Page_BugsUI Edit Product/button_Delete Product\u0027 successfully","description":"","startTime":1556785605007,"endTime":1556785605129,"childRecords":[{"testStatus":{"stackTrace":"","statusValue":"PASSED"},"type":"MESSAGE","name":"","message":"Scroll to object \u0027Object Repository/Page_BugsUI Edit Product/button_Delete Product\u0027 successfully","startTime":1556785605128,"endTime":0,"childRecords":[],"interuppted":false}],"interuppted":false},{"index":15,"isIgnoredIfFailed":false,"type":"TEST_STEP","name":"verifyElementPresent","message":"Object \u0027Object Repository/Page_BugsUI Edit Product/div_Component Information\u0027 is present","description":"","startTime":1556785605129,"endTime":1556785605167,"childRecords":[{"testStatus":{"stackTrace":"","statusValue":"WARNING"},"type":"MESSAGE","name":"","message":"Timeout \u00270\u0027 is invalid. Using default page load timeout: \u002730\u0027","startTime":1556785605134,"endTime":0,"childRecords":[],"interuppted":false},{"testStatus":{"stackTrace":"","statusValue":"PASSED"},"type":"MESSAGE","name":"","message":"Object \u0027Object Repository/Page_BugsUI Edit Product/div_Component Information\u0027 is present","startTime":1556785605166,"endTime":0,"childRecords":[],"interuppted":false}],"interuppted":false},{"index":16,"isIgnoredIfFailed":false,"type":"TEST_STEP","name":"verifyElementPresent","message":"Object \u0027Object Repository/Page_BugsUI Edit Product/button_Refresh components\u0027 is present","description":"","startTime":1556785605167,"endTime":1556785605232,"childRecords":[{"testStatus":{"stackTrace":"","statusValue":"WARNING"},"type":"MESSAGE","name":"","message":"Timeout \u00270\u0027 is invalid. Using default page load timeout: \u002730\u0027","startTime":1556785605172,"endTime":0,"childRecords":[],"interuppted":false},{"testStatus":{"stackTrace":"","statusValue":"PASSED"},"type":"MESSAGE","name":"","message":"Object \u0027Object Repository/Page_BugsUI Edit Product/button_Refresh components\u0027 is present","startTime":1556785605232,"endTime":0,"childRecords":[],"interuppted":false}],"interuppted":false},{"index":17,"isIgnoredIfFailed":false,"type":"TEST_STEP","name":"verifyElementPresent","message":"Object \u0027Object Repository/Page_BugsUI Edit Product/button_AddNewRow_Component\u0027 is present","description":"","startTime":1556785605232,"endTime":1556785605262,"childRecords":[{"testStatus":{"stackTrace":"","statusValue":"WARNING"},"type":"MESSAGE","name":"","message":"Timeout \u00270\u0027 is invalid. Using default page load timeout: \u002730\u0027","startTime":1556785605232,"endTime":0,"childRecords":[],"interuppted":false},{"testStatus":{"stackTrace":"","statusValue":"PASSED"},"type":"MESSAGE","name":"","message":"Object \u0027Object Repository/Page_BugsUI Edit Product/button_AddNewRow_Component\u0027 is present","startTime":1556785605262,"endTime":0,"childRecords":[],"interuppted":false}],"interuppted":false},{"index":18,"isIgnoredIfFailed":false,"type":"TEST_STEP","name":"verifyElementPresent","message":"Object \u0027Object Repository/Page_BugsUI Edit Product/span_Version Information\u0027 is present","description":"","startTime":1556785605262,"endTime":1556785605309,"childRecords":[{"testStatus":{"stackTrace":"","statusValue":"WARNING"},"type":"MESSAGE","name":"","message":"Timeout \u00270\u0027 is invalid. Using default page load timeout: \u002730\u0027","startTime":1556785605262,"endTime":0,"childRecords":[],"interuppted":false},{"testStatus":{"stackTrace":"","statusValue":"PASSED"},"type":"MESSAGE","name":"","message":"Object \u0027Object Repository/Page_BugsUI Edit Product/span_Version Information\u0027 is present","startTime":1556785605309,"endTime":0,"childRecords":[],"interuppted":false}],"interuppted":false},{"index":19,"isIgnoredIfFailed":false,"type":"TEST_STEP","name":"verifyElementPresent","message":"Object \u0027Object Repository/Page_BugsUI Edit Product/button_Refresh versions\u0027 is present","description":"","startTime":1556785605309,"endTime":1556785605358,"childRecords":[{"testStatus":{"stackTrace":"","statusValue":"WARNING"},"type":"MESSAGE","name":"","message":"Timeout \u00270\u0027 is invalid. Using default page load timeout: \u002730\u0027","startTime":1556785605323,"endTime":0,"childRecords":[],"interuppted":false},{"testStatus":{"stackTrace":"","statusValue":"PASSED"},"type":"MESSAGE","name":"","message":"Object \u0027Object Repository/Page_BugsUI Edit Product/button_Refresh versions\u0027 is present","startTime":1556785605358,"endTime":0,"childRecords":[],"interuppted":false}],"interuppted":false},{"index":20,"isIgnoredIfFailed":false,"type":"TEST_STEP","name":"verifyElementPresent","message":"Object \u0027Object Repository/Page_BugsUI Edit Product/button_AddNewRow_version\u0027 is present","description":"","startTime":1556785605358,"endTime":1556785605394,"childRecords":[{"testStatus":{"stackTrace":"","statusValue":"WARNING"},"type":"MESSAGE","name":"","message":"Timeout \u00270\u0027 is invalid. Using default page load timeout: \u002730\u0027","startTime":1556785605358,"endTime":0,"childRecords":[],"interuppted":false},{"testStatus":{"stackTrace":"","statusValue":"PASSED"},"type":"MESSAGE","name":"","message":"Object \u0027Object Repository/Page_BugsUI Edit Product/button_AddNewRow_version\u0027 is present","startTime":1556785605394,"endTime":0,"childRecords":[],"interuppted":false}],"interuppted":false},{"index":21,"isIgnoredIfFailed":false,"type":"TEST_STEP","name":"delay","message":"Delayed 2 second(s)","description":"","startTime":1556785605394,"endTime":1556785607395,"childRecords":[{"testStatus":{"stackTrace":"","statusValue":"PASSED"},"type":"MESSAGE","name":"","message":"Delayed 2 second(s)","startTime":1556785607395,"endTime":0,"childRecords":[],"interuppted":false}],"interuppted":false},{"testStatus":{"stackTrace":"","statusValue":"PASSED"},"type":"MESSAGE","name":"","message":"Test Cases/Edit_Product/Edit_product_fields","startTime":1556785607395,"endTime":0,"childRecords":[],"interuppted":false}],"interuppted":false},{"isOptional":false,"type":"TEST_CASE","name":"Test Cases/Edit_Product/verify_values_prepopulated","id":"Test Cases/Edit_Product/verify_values_prepopulated","source":"C:\\\\New-Bugzilla-Application\\\\New_Bugzilla-UI-V2\\\\Test Cases\\\\Edit_Product\\\\verify_values_prepopulated.tc","message":"Test Cases/Edit_Product/verify_values_prepopulated","description":"","startTime":1556785607399,"endTime":1556785609980,"childRecords":[{"testStatus":{"stackTrace":"","statusValue":"INFO"},"type":"MESSAGE","name":"","message":"Evaluating variables for test case","startTime":1556785607403,"endTime":0,"childRecords":[],"interuppted":false},{"index":1,"isIgnoredIfFailed":false,"type":"TEST_STEP","name":"scrollToElement","message":"Scroll to object \u0027Object Repository/Page_BugsUI Edit Product/input_newName\u0027 successfully","description":"","startTime":1556785607665,"endTime":1556785607703,"childRecords":[{"testStatus":{"stackTrace":"","statusValue":"PASSED"},"type":"MESSAGE","name":"","message":"Scroll to object \u0027Object Repository/Page_BugsUI Edit Product/input_newName\u0027 successfully","startTime":1556785607703,"endTime":0,"childRecords":[],"interuppted":false}],"interuppted":false},{"index":2,"isIgnoredIfFailed":false,"type":"TEST_STEP","name":"Statement - productName \u003d com.kms.katalon.core.webui.keyword.WebUiBuiltInKeywords.getAttribute(com.kms.katalon.core.testobject.ObjectRepository.findTestObject(Page_BugsUI Edit Product/input_newName), \"value\")","message":"Attribute \u0027value\u0027 of object \u0027Object Repository/Page_BugsUI Edit Product/input_newName\u0027 is: \u00271-Auto-edit\u0027","description":"","startTime":1556785607704,"endTime":1556785607752,"childRecords":[{"testStatus":{"stackTrace":"","statusValue":"PASSED"},"type":"MESSAGE","name":"","message":"Attribute \u0027value\u0027 of object \u0027Object Repository/Page_BugsUI Edit Product/input_newName\u0027 is: \u00271-Auto-edit\u0027","startTime":1556785607752,"endTime":0,"childRecords":[],"interuppted":false}],"interuppted":false},{"index":3,"isIgnoredIfFailed":false,"type":"TEST_STEP","name":"Statement - productDescription \u003d com.kms.katalon.core.webui.keyword.WebUiBuiltInKeywords.getAttribute(com.kms.katalon.core.testobject.ObjectRepository.findTestObject(Page_BugsUI Edit Product/textarea_description), \"value\")","message":"Attribute \u0027value\u0027 of object \u0027Object Repository/Page_BugsUI Edit Product/textarea_description\u0027 is: \u0027This product created for Automation of Edit page functionalities.\u0027","description":"","startTime":1556785607753,"endTime":1556785607797,"childRecords":[{"testStatus":{"stackTrace":"","statusValue":"PASSED"},"type":"MESSAGE","name":"","message":"Attribute \u0027value\u0027 of object \u0027Object Repository/Page_BugsUI Edit Product/textarea_description\u0027 is: \u0027This product created for Automation of Edit page functionalities.\u0027","startTime":1556785607797,"endTime":0,"childRecords":[],"interuppted":false}],"interuppted":false},{"index":4,"isIgnoredIfFailed":false,"type":"TEST_STEP","name":"Statement - If (productName.equals(\"1-Auto-edit\"))","description":"","startTime":1556785607797,"endTime":1556785607797,"childRecords":[{"index":1,"isIgnoredIfFailed":false,"type":"TEST_STEP","name":"Statement - assert true","description":"","startTime":1556785607797,"endTime":1556785607797,"childRecords":[],"interuppted":false}],"interuppted":false},{"index":6,"isIgnoredIfFailed":false,"type":"TEST_STEP","name":"Statement - If (!(productDescription.isEmpty()))","description":"","startTime":1556785607797,"endTime":1556785607797,"childRecords":[{"index":1,"isIgnoredIfFailed":false,"type":"TEST_STEP","name":"Statement - assert true","description":"","startTime":1556785607797,"endTime":1556785607797,"childRecords":[],"interuppted":false}],"interuppted":false},{"index":8,"isIgnoredIfFailed":false,"type":"TEST_STEP","name":"verifyElementNotClickable","message":"Object \u0027Object Repository/Page_BugsUI Edit Product/unknown_Component\u0027 is NOT clickable","description":"","startTime":1556785607797,"endTime":1556785607844,"childRecords":[{"testStatus":{"stackTrace":"","statusValue":"PASSED"},"type":"MESSAGE","name":"","message":"Object \u0027Object Repository/Page_BugsUI Edit Product/unknown_Component\u0027 is NOT clickable","startTime":1556785607844,"endTime":0,"childRecords":[],"interuppted":false}],"interuppted":false},{"index":9,"isIgnoredIfFailed":false,"type":"TEST_STEP","name":"Statement - unkownComponentName \u003d com.kms.katalon.core.webui.keyword.WebUiBuiltInKeywords.getAttribute(com.kms.katalon.core.testobject.ObjectRepository.findTestObject(Page_BugsUI Edit Product/unknown_Component), \"value\")","message":"Attribute \u0027value\u0027 of object \u0027Object Repository/Page_BugsUI Edit Product/unknown_Component\u0027 is: \u0027Unknown\u0027","description":"","startTime":1556785607844,"endTime":1556785607886,"childRecords":[{"testStatus":{"stackTrace":"","statusValue":"PASSED"},"type":"MESSAGE","name":"","message":"Attribute \u0027value\u0027 of object \u0027Object Repository/Page_BugsUI Edit Product/unknown_Component\u0027 is: \u0027Unknown\u0027","startTime":1556785607886,"endTime":0,"childRecords":[],"interuppted":false}],"interuppted":false},{"index":10,"isIgnoredIfFailed":false,"type":"TEST_STEP","name":"Statement - If (unkownComponentName.equals(\"Unknown\"))","description":"","startTime":1556785607886,"endTime":1556785607894,"childRecords":[{"index":1,"isIgnoredIfFailed":false,"type":"TEST_STEP","name":"Statement - assert true","description":"","startTime":1556785607894,"endTime":1556785607894,"childRecords":[],"interuppted":false}],"interuppted":false},{"index":12,"isIgnoredIfFailed":false,"type":"TEST_STEP","name":"Statement - unkownComponentDesc \u003d com.kms.katalon.core.webui.keyword.WebUiBuiltInKeywords.getAttribute(com.kms.katalon.core.testobject.ObjectRepository.findTestObject(Page_BugsUI Edit Product/unkown_description), \"value\")","message":"Attribute \u0027value\u0027 of object \u0027Object Repository/Page_BugsUI Edit Product/unkown_description\u0027 is: \u0027unknown\u0027","description":"","startTime":1556785607895,"endTime":1556785607928,"childRecords":[{"testStatus":{"stackTrace":"","statusValue":"PASSED"},"type":"MESSAGE","name":"","message":"Attribute \u0027value\u0027 of object \u0027Object Repository/Page_BugsUI Edit Product/unkown_description\u0027 is: \u0027unknown\u0027","startTime":1556785607928,"endTime":0,"childRecords":[],"interuppted":false}],"interuppted":false},{"index":13,"isIgnoredIfFailed":false,"type":"TEST_STEP","name":"Statement - unkownComponentDefaultAsignee \u003d com.kms.katalon.core.webui.keyword.WebUiBuiltInKeywords.getAttribute(com.kms.katalon.core.testobject.ObjectRepository.findTestObject(Page_BugsUI Edit Product/unkown_defaultAssignee), \"value\")","message":"Attribute \u0027value\u0027 of object \u0027Object Repository/Page_BugsUI Edit Product/unkown_defaultAssignee\u0027 is: \u0027kumar.nagendra@happiestminds.com\u0027","description":"","startTime":1556785607928,"endTime":1556785607971,"childRecords":[{"testStatus":{"stackTrace":"","statusValue":"PASSED"},"type":"MESSAGE","name":"","message":"Attribute \u0027value\u0027 of object \u0027Object Repository/Page_BugsUI Edit Product/unkown_defaultAssignee\u0027 is: \u0027kumar.nagendra@happiestminds.com\u0027","startTime":1556785607971,"endTime":0,"childRecords":[],"interuppted":false}],"interuppted":false},{"index":14,"isIgnoredIfFailed":false,"type":"TEST_STEP","name":"Statement - If (!(unkownComponentDesc.isEmpty()) \u0026\u0026 !(unkownComponentDefaultAsignee.isEmpty()))","description":"","startTime":1556785607971,"endTime":1556785607978,"childRecords":[{"index":1,"isIgnoredIfFailed":false,"type":"TEST_STEP","name":"Statement - assert true","description":"","startTime":1556785607971,"endTime":1556785607971,"childRecords":[],"interuppted":false}],"interuppted":false},{"index":16,"isIgnoredIfFailed":false,"type":"TEST_STEP","name":"delay","message":"Delayed 2 second(s)","description":"","startTime":1556785607978,"endTime":1556785609980,"childRecords":[{"testStatus":{"stackTrace":"","statusValue":"PASSED"},"type":"MESSAGE","name":"","message":"Delayed 2 second(s)","startTime":1556785609980,"endTime":0,"childRecords":[],"interuppted":false}],"interuppted":false},{"testStatus":{"stackTrace":"","statusValue":"PASSED"},"type":"MESSAGE","name":"","message":"Test Cases/Edit_Product/verify_values_prepopulated","startTime":1556785609980,"endTime":0,"childRecords":[],"interuppted":false}],"interuppted":false},{"isOptional":false,"type":"TEST_CASE","name":"Test Cases/Edit_Product/default_UnknownComponent","id":"Test Cases/Edit_Product/default_UnknownComponent","source":"C:\\\\New-Bugzilla-Application\\\\New_Bugzilla-UI-V2\\\\Test Cases\\\\Edit_Product\\\\default_UnknownComponent.tc","message":"Test Cases/Edit_Product/default_UnknownComponent","description":"","startTime":1556785609982,"endTime":1556785629820,"childRecords":[{"testStatus":{"stackTrace":"","statusValue":"INFO"},"type":"MESSAGE","name":"","message":"Evaluating variables for test case","startTime":1556785610006,"endTime":0,"childRecords":[],"interuppted":false},{"index":1,"isIgnoredIfFailed":false,"type":"TEST_STEP","name":"Statement - If (com.kms.katalon.core.webui.keyword.WebUiBuiltInKeywords.verifyElementPresent(com.kms.katalon.core.testobject.ObjectRepository.findTestObject(Page_BugsUI Edit Product/delete_icon_unknownCompnent), 0))","message":"Object: \u0027Object Repository/Page_BugsUI Edit Product/delete_icon_unknownCompnent\u0027 is clicked on","description":"","startTime":1556785610248,"endTime":1556785610415,"childRecords":[{"testStatus":{"stackTrace":"","statusValue":"WARNING"},"type":"MESSAGE","name":"","message":"Timeout \u00270\u0027 is invalid. Using default page load timeout: \u002730\u0027","startTime":1556785610255,"endTime":0,"childRecords":[],"interuppted":false},{"testStatus":{"stackTrace":"","statusValue":"PASSED"},"type":"MESSAGE","name":"","message":"Object \u0027Object Repository/Page_BugsUI Edit Product/delete_icon_unknownCompnent\u0027 is present","startTime":1556785610280,"endTime":0,"childRecords":[],"interuppted":false},{"index":1,"isIgnoredIfFailed":false,"type":"TEST_STEP","name":"click","message":"Object: \u0027Object Repository/Page_BugsUI Edit Product/delete_icon_unknownCompnent\u0027 is clicked on","description":"","startTime":1556785610280,"endTime":1556785610415,"childRecords":[{"testStatus":{"stackTrace":"","statusValue":"PASSED"},"type":"MESSAGE","name":"","message":"Object: \u0027Object Repository/Page_BugsUI Edit Product/delete_icon_unknownCompnent\u0027 is clicked on","startTime":1556785610413,"endTime":0,"childRecords":[],"interuppted":false}],"interuppted":false}],"interuppted":false},{"index":2,"isIgnoredIfFailed":false,"type":"TEST_STEP","name":"delay","message":"Delayed 2 second(s)","description":"","startTime":1556785610415,"endTime":1556785612416,"childRecords":[{"testStatus":{"stackTrace":"","statusValue":"PASSED"},"type":"MESSAGE","name":"","message":"Delayed 2 second(s)","startTime":1556785612416,"endTime":0,"childRecords":[],"interuppted":false}],"interuppted":false},{"index":3,"isIgnoredIfFailed":false,"type":"TEST_STEP","name":"Statement - If (com.kms.katalon.core.webui.keyword.WebUiBuiltInKeywords.verifyElementPresent(com.kms.katalon.core.testobject.ObjectRepository.findTestObject(Page_BugsUI Edit Product/confirmDeleteProduct_popup), 0))","message":"Object: \u0027Object Repository/Page_BugsUI Edit Product/button_component_Yes\u0027 is clicked on","description":"","startTime":1556785612417,"endTime":1556785612589,"childRecords":[{"testStatus":{"stackTrace":"","statusValue":"WARNING"},"type":"MESSAGE","name":"","message":"Timeout \u00270\u0027 is invalid. Using default page load timeout: \u002730\u0027","startTime":1556785612420,"endTime":0,"childRecords":[],"interuppted":false},{"testStatus":{"stackTrace":"","statusValue":"PASSED"},"type":"MESSAGE","name":"","message":"Object \u0027Object Repository/Page_BugsUI Edit Product/confirmDeleteProduct_popup\u0027 is present","startTime":1556785612447,"endTime":0,"childRecords":[],"interuppted":false},{"index":1,"isIgnoredIfFailed":false,"type":"TEST_STEP","name":"Statement - If (com.kms.katalon.core.webui.keyword.WebUiBuiltInKeywords.verifyElementPresent(com.kms.katalon.core.testobject.ObjectRepository.findTestObject(Page_BugsUI Edit Product/button_component_Yes), 0))","message":"Object: \u0027Object Repository/Page_BugsUI Edit Product/button_component_Yes\u0027 is clicked on","description":"","startTime":1556785612447,"endTime":1556785612589,"childRecords":[{"testStatus":{"stackTrace":"","statusValue":"WARNING"},"type":"MESSAGE","name":"","message":"Timeout \u00270\u0027 is invalid. Using default page load timeout: \u002730\u0027","startTime":1556785612459,"endTime":0,"childRecords":[],"interuppted":false},{"testStatus":{"stackTrace":"","statusValue":"PASSED"},"type":"MESSAGE","name":"","message":"Object \u0027Object Repository/Page_BugsUI Edit Product/button_component_Yes\u0027 is present","startTime":1556785612483,"endTime":0,"childRecords":[],"interuppted":false},{"index":1,"isIgnoredIfFailed":false,"type":"TEST_STEP","name":"click","message":"Object: \u0027Object Repository/Page_BugsUI Edit Product/button_component_Yes\u0027 is clicked on","description":"","startTime":1556785612483,"endTime":1556785612588,"childRecords":[{"testStatus":{"stackTrace":"","statusValue":"PASSED"},"type":"MESSAGE","name":"","message":"Object: \u0027Object Repository/Page_BugsUI Edit Product/button_component_Yes\u0027 is clicked on","startTime":1556785612588,"endTime":0,"childRecords":[],"interuppted":false}],"interuppted":false}],"interuppted":false}],"interuppted":false},{"index":4,"isIgnoredIfFailed":false,"type":"TEST_STEP","name":"delay","message":"Delayed 2 second(s)","description":"","startTime":1556785612589,"endTime":1556785614591,"childRecords":[{"testStatus":{"stackTrace":"","statusValue":"PASSED"},"type":"MESSAGE","name":"","message":"Delayed 2 second(s)","startTime":1556785614591,"endTime":0,"childRecords":[],"interuppted":false}],"interuppted":false},{"index":5,"isIgnoredIfFailed":false,"type":"TEST_STEP","name":"Statement - If (com.kms.katalon.core.webui.keyword.WebUiBuiltInKeywords.verifyElementPresent(com.kms.katalon.core.testobject.ObjectRepository.findTestObject(Page_BugsUI Edit Product/div_Product_atleast_1_component), 0))","description":"","startTime":1556785614591,"endTime":1556785614712,"childRecords":[{"testStatus":{"stackTrace":"","statusValue":"WARNING"},"type":"MESSAGE","name":"","message":"Timeout \u00270\u0027 is invalid. Using default page load timeout: \u002730\u0027","startTime":1556785614594,"endTime":0,"childRecords":[],"interuppted":false},{"testStatus":{"stackTrace":"","statusValue":"PASSED"},"type":"MESSAGE","name":"","message":"Object \u0027Object Repository/Page_BugsUI Edit Product/div_Product_atleast_1_component\u0027 is present","startTime":1556785614637,"endTime":0,"childRecords":[],"interuppted":false},{"index":1,"isIgnoredIfFailed":false,"type":"TEST_STEP","name":"Statement - warningMessage \u003d com.kms.katalon.core.webui.keyword.WebUiBuiltInKeywords.getText(com.kms.katalon.core.testobject.ObjectRepository.findTestObject(Page_BugsUI Edit Product/div_Product_atleast_1_component))","message":"Text of object \u0027Object Repository/Page_BugsUI Edit Product/div_Product_atleast_1_component\u0027 is: \u0027Product must have at least 1 component.\u0027","description":"","startTime":1556785614637,"endTime":1556785614712,"childRecords":[{"testStatus":{"stackTrace":"","statusValue":"PASSED"},"type":"MESSAGE","name":"","message":"Text of object \u0027Object Repository/Page_BugsUI Edit Product/div_Product_atleast_1_component\u0027 is: \u0027Product must have at least 1 component.\u0027","startTime":1556785614712,"endTime":0,"childRecords":[],"interuppted":false}],"interuppted":false},{"index":2,"isIgnoredIfFailed":false,"type":"TEST_STEP","name":"Statement - If (warningMessage.equals(\"Product must have at least 1 component.\"))","description":"","startTime":1556785614712,"endTime":1556785614712,"childRecords":[{"index":1,"isIgnoredIfFailed":false,"type":"TEST_STEP","name":"Statement - assert true","description":"","startTime":1556785614712,"endTime":1556785614712,"childRecords":[],"interuppted":false}],"interuppted":false}],"interuppted":false},{"index":6,"isIgnoredIfFailed":false,"type":"TEST_STEP","name":"delay","message":"Delayed 3 second(s)","description":"","startTime":1556785614712,"endTime":1556785617714,"childRecords":[{"testStatus":{"stackTrace":"","statusValue":"PASSED"},"type":"MESSAGE","name":"","message":"Delayed 3 second(s)","startTime":1556785617714,"endTime":0,"childRecords":[],"interuppted":false}],"interuppted":false},{"index":7,"isIgnoredIfFailed":false,"type":"TEST_STEP","name":"Statement - If (com.kms.katalon.core.webui.keyword.WebUiBuiltInKeywords.verifyElementPresent(com.kms.katalon.core.testobject.ObjectRepository.findTestObject(Page_BugsUI Edit Product/update_icon_unknownComponent), 0))","description":"","startTime":1556785617714,"endTime":1556785618023,"childRecords":[{"testStatus":{"stackTrace":"","statusValue":"WARNING"},"type":"MESSAGE","name":"","message":"Timeout \u00270\u0027 is invalid. Using default page load timeout: \u002730\u0027","startTime":1556785617717,"endTime":0,"childRecords":[],"interuppted":false},{"testStatus":{"stackTrace":"","statusValue":"PASSED"},"type":"MESSAGE","name":"","message":"Object \u0027Object Repository/Page_BugsUI Edit Product/update_icon_unknownComponent\u0027 is present","startTime":1556785617742,"endTime":0,"childRecords":[],"interuppted":false},{"index":1,"isIgnoredIfFailed":false,"type":"TEST_STEP","name":"click","message":"Object: \u0027Object Repository/Page_BugsUI Edit Product/update_icon_unknownComponent\u0027 is clicked on","description":"","startTime":1556785617742,"endTime":1556785617889,"childRecords":[{"testStatus":{"stackTrace":"","statusValue":"PASSED"},"type":"MESSAGE","name":"","message":"Object: \u0027Object Repository/Page_BugsUI Edit Product/update_icon_unknownComponent\u0027 is clicked on","startTime":1556785617888,"endTime":0,"childRecords":[],"interuppted":false}],"interuppted":false},{"index":2,"isIgnoredIfFailed":false,"type":"TEST_STEP","name":"Statement - If (com.kms.katalon.core.webui.keyword.WebUiBuiltInKeywords.verifyElementPresent(com.kms.katalon.core.testobject.ObjectRepository.findTestObject(Page_BugsUI Edit Product/div_Nothing to update), 0))","description":"","startTime":1556785617889,"endTime":1556785618023,"childRecords":[{"testStatus":{"stackTrace":"","statusValue":"WARNING"},"type":"MESSAGE","name":"","message":"Timeout \u00270\u0027 is invalid. Using default page load timeout: \u002730\u0027","startTime":1556785617895,"endTime":0,"childRecords":[],"interuppted":false},{"testStatus":{"stackTrace":"","statusValue":"PASSED"},"type":"MESSAGE","name":"","message":"Object \u0027Object Repository/Page_BugsUI Edit Product/div_Nothing to update\u0027 is present","startTime":1556785617956,"endTime":0,"childRecords":[],"interuppted":false},{"index":1,"isIgnoredIfFailed":false,"type":"TEST_STEP","name":"Statement - nothingToUpdate \u003d com.kms.katalon.core.webui.keyword.WebUiBuiltInKeywords.getText(com.kms.katalon.core.testobject.ObjectRepository.findTestObject(Page_BugsUI Edit Product/div_Nothing to update))","message":"Text of object \u0027Object Repository/Page_BugsUI Edit Product/div_Nothing to update\u0027 is: \u0027Nothing to update.\u0027","description":"","startTime":1556785617956,"endTime":1556785618021,"childRecords":[{"testStatus":{"stackTrace":"","statusValue":"PASSED"},"type":"MESSAGE","name":"","message":"Text of object \u0027Object Repository/Page_BugsUI Edit Product/div_Nothing to update\u0027 is: \u0027Nothing to update.\u0027","startTime":1556785618021,"endTime":0,"childRecords":[],"interuppted":false}],"interuppted":false},{"index":2,"isIgnoredIfFailed":false,"type":"TEST_STEP","name":"Statement - If (nothingToUpdate.equals(\"Nothing to update.\"))","description":"","startTime":1556785618022,"endTime":1556785618023,"childRecords":[{"index":1,"isIgnoredIfFailed":false,"type":"TEST_STEP","name":"Statement - assert true","description":"","startTime":1556785618022,"endTime":1556785618022,"childRecords":[],"interuppted":false}],"interuppted":false}],"interuppted":false}],"interuppted":false},{"index":8,"isIgnoredIfFailed":false,"type":"TEST_STEP","name":"clearText","message":"Text of object \u0027Object Repository/Page_BugsUI Edit Product/unkown_description\u0027 is cleared","description":"","startTime":1556785618024,"endTime":1556785618121,"childRecords":[{"testStatus":{"stackTrace":"","statusValue":"PASSED"},"type":"MESSAGE","name":"","message":"Text of object \u0027Object Repository/Page_BugsUI Edit Product/unkown_description\u0027 is cleared","startTime":1556785618121,"endTime":0,"childRecords":[],"interuppted":false}],"interuppted":false},{"index":9,"isIgnoredIfFailed":false,"type":"TEST_STEP","name":"setText","message":"Text \u0027unknown1234\u0027 is set on object \u0027Object Repository/Page_BugsUI Edit Product/unkown_description\u0027","description":"","startTime":1556785618122,"endTime":1556785618372,"childRecords":[{"testStatus":{"stackTrace":"","statusValue":"PASSED"},"type":"MESSAGE","name":"","message":"Text \u0027unknown1234\u0027 is set on object \u0027Object Repository/Page_BugsUI Edit Product/unkown_description\u0027","startTime":1556785618371,"endTime":0,"childRecords":[],"interuppted":false}],"interuppted":false},{"index":10,"isIgnoredIfFailed":false,"type":"TEST_STEP","name":"clearText","message":"Text of object \u0027Object Repository/Page_BugsUI Edit Product/unkown_defaultAssignee\u0027 is cleared","description":"","startTime":1556785618372,"endTime":1556785618454,"childRecords":[{"testStatus":{"stackTrace":"","statusValue":"PASSED"},"type":"MESSAGE","name":"","message":"Text of object \u0027Object Repository/Page_BugsUI Edit Product/unkown_defaultAssignee\u0027 is cleared","startTime":1556785618454,"endTime":0,"childRecords":[],"interuppted":false}],"interuppted":false},{"index":11,"isIgnoredIfFailed":false,"type":"TEST_STEP","name":"setText","message":"Text \u0027divya.r@happiestminds.com\u0027 is set on object \u0027Object Repository/Page_BugsUI Edit Product/unkown_defaultAssignee\u0027","description":"","startTime":1556785618454,"endTime":1556785618791,"childRecords":[{"testStatus":{"stackTrace":"","statusValue":"PASSED"},"type":"MESSAGE","name":"","message":"Text \u0027divya.r@happiestminds.com\u0027 is set on object \u0027Object Repository/Page_BugsUI Edit Product/unkown_defaultAssignee\u0027","startTime":1556785618790,"endTime":0,"childRecords":[],"interuppted":false}],"interuppted":false},{"index":12,"isIgnoredIfFailed":false,"type":"TEST_STEP","name":"click","message":"Object: \u0027Object Repository/Page_BugsUI Edit Product/update_icon_unknownComponent\u0027 is clicked on","description":"","startTime":1556785618791,"endTime":1556785618890,"childRecords":[{"testStatus":{"stackTrace":"","statusValue":"PASSED"},"type":"MESSAGE","name":"","message":"Object: \u0027Object Repository/Page_BugsUI Edit Product/update_icon_unknownComponent\u0027 is clicked on","startTime":1556785618889,"endTime":0,"childRecords":[],"interuppted":false}],"interuppted":false},{"index":13,"isIgnoredIfFailed":false,"type":"TEST_STEP","name":"Statement - If (com.kms.katalon.core.webui.keyword.WebUiBuiltInKeywords.verifyElementPresent(com.kms.katalon.core.testobject.ObjectRepository.findTestObject(Page_BugsUI Edit Product/div_Component has been updated), 0))","description":"","startTime":1556785618890,"endTime":1556785620006,"childRecords":[{"testStatus":{"stackTrace":"","statusValue":"WARNING"},"type":"MESSAGE","name":"","message":"Timeout \u00270\u0027 is invalid. Using default page load timeout: \u002730\u0027","startTime":1556785618895,"endTime":0,"childRecords":[],"interuppted":false},{"testStatus":{"stackTrace":"","statusValue":"PASSED"},"type":"MESSAGE","name":"","message":"Object \u0027Object Repository/Page_BugsUI Edit Product/div_Component has been updated\u0027 is present","startTime":1556785619967,"endTime":0,"childRecords":[],"interuppted":false},{"index":1,"isIgnoredIfFailed":false,"type":"TEST_STEP","name":"Statement - componentUpdatedMsg \u003d com.kms.katalon.core.webui.keyword.WebUiBuiltInKeywords.getText(com.kms.katalon.core.testobject.ObjectRepository.findTestObject(Page_BugsUI Edit Product/div_Component has been updated))","message":"Text of object \u0027Object Repository/Page_BugsUI Edit Product/div_Component has been updated\u0027 is: \u0027Component has been updated successfully.\u0027","description":"","startTime":1556785619967,"endTime":1556785620004,"childRecords":[{"testStatus":{"stackTrace":"","statusValue":"PASSED"},"type":"MESSAGE","name":"","message":"Text of object \u0027Object Repository/Page_BugsUI Edit Product/div_Component has been updated\u0027 is: \u0027Component has been updated successfully.\u0027","startTime":1556785620004,"endTime":0,"childRecords":[],"interuppted":false}],"interuppted":false},{"index":2,"isIgnoredIfFailed":false,"type":"TEST_STEP","name":"Statement - If (componentUpdatedMsg.equals(\"Component has been updated successfully.\"))","description":"","startTime":1556785620005,"endTime":1556785620006,"childRecords":[{"index":1,"isIgnoredIfFailed":false,"type":"TEST_STEP","name":"Statement - assert true","description":"","startTime":1556785620005,"endTime":1556785620005,"childRecords":[],"interuppted":false}],"interuppted":false}],"interuppted":false},{"index":14,"isIgnoredIfFailed":false,"type":"TEST_STEP","name":"delay","message":"Delayed 4 second(s)","description":"","startTime":1556785620006,"endTime":1556785624008,"childRecords":[{"testStatus":{"stackTrace":"","statusValue":"PASSED"},"type":"MESSAGE","name":"","message":"Delayed 4 second(s)","startTime":1556785624008,"endTime":0,"childRecords":[],"interuppted":false}],"interuppted":false},{"index":15,"isIgnoredIfFailed":false,"type":"TEST_STEP","name":"reusable.editPage.resetUnkownComponent","message":"reusable.editPage.resetUnkownComponent is PASSED","description":"","startTime":1556785624009,"endTime":1556785626815,"childRecords":[{"testStatus":{"stackTrace":"","statusValue":"PASSED"},"type":"MESSAGE","name":"","message":"Text of object \u0027Object Repository/Page_BugsUI Edit Product/unkown_description\u0027 is cleared","startTime":1556785624054,"endTime":0,"childRecords":[],"interuppted":false},{"testStatus":{"stackTrace":"","statusValue":"PASSED"},"type":"MESSAGE","name":"","message":"Text \u0027unknown\u0027 is set on object \u0027Object Repository/Page_BugsUI Edit Product/unkown_description\u0027","startTime":1556785624262,"endTime":0,"childRecords":[],"interuppted":false},{"testStatus":{"stackTrace":"","statusValue":"PASSED"},"type":"MESSAGE","name":"","message":"Text of object \u0027Object Repository/Page_BugsUI Edit Product/unkown_defaultAssignee\u0027 is cleared","startTime":1556785624306,"endTime":0,"childRecords":[],"interuppted":false},{"testStatus":{"stackTrace":"","statusValue":"PASSED"},"type":"MESSAGE","name":"","message":"Text \u0027kumar.nagendra@happiestminds.com\u0027 is set on object \u0027Object Repository/Page_BugsUI Edit Product/unkown_defaultAssignee\u0027","startTime":1556785624714,"endTime":0,"childRecords":[],"interuppted":false},{"testStatus":{"stackTrace":"","statusValue":"PASSED"},"type":"MESSAGE","name":"","message":"Object: \u0027Object Repository/Page_BugsUI Edit Product/update_icon_unknownComponent\u0027 is clicked on","startTime":1556785624813,"endTime":0,"childRecords":[],"interuppted":false},{"testStatus":{"stackTrace":"","statusValue":"PASSED"},"type":"MESSAGE","name":"","message":"Delayed 2 second(s)","startTime":1556785626815,"endTime":0,"childRecords":[],"interuppted":false},{"testStatus":{"stackTrace":"","statusValue":"PASSED"},"type":"MESSAGE","name":"","message":"reusable.editPage.resetUnkownComponent is PASSED","startTime":1556785626815,"endTime":0,"childRecords":[],"interuppted":false}],"interuppted":false},{"index":16,"isIgnoredIfFailed":false,"type":"TEST_STEP","name":"delay","message":"Delayed 3 second(s)","description":"","startTime":1556785626815,"endTime":1556785629818,"childRecords":[{"testStatus":{"stackTrace":"","statusValue":"PASSED"},"type":"MESSAGE","name":"","message":"Delayed 3 second(s)","startTime":1556785629817,"endTime":0,"childRecords":[],"interuppted":false}],"interuppted":false},{"testStatus":{"stackTrace":"","statusValue":"PASSED"},"type":"MESSAGE","name":"","message":"Test Cases/Edit_Product/default_UnknownComponent","startTime":1556785629819,"endTime":0,"childRecords":[],"interuppted":false}],"interuppted":false},{"isOptional":false,"type":"TEST_CASE","name":"Test Cases/Edit_Product/component_section","id":"Test Cases/Edit_Product/component_section","source":"C:\\\\New-Bugzilla-Application\\\\New_Bugzilla-UI-V2\\\\Test Cases\\\\Edit_Product\\\\component_section.tc","message":"Test Cases/Edit_Product/component_section","description":"","startTime":1556785629833,"endTime":1556785650579,"childRecords":[{"testStatus":{"stackTrace":"","statusValue":"INFO"},"type":"MESSAGE","name":"","message":"Evaluating variables for test case","startTime":1556785629875,"endTime":0,"childRecords":[],"interuppted":false},{"index":1,"isIgnoredIfFailed":false,"type":"TEST_STEP","name":"Statement - If (com.kms.katalon.core.webui.keyword.WebUiBuiltInKeywords.verifyElementPresent(com.kms.katalon.core.testobject.ObjectRepository.findTestObject(Page_BugsUI Edit Product/button_AddNewRow_Component), 0))","message":"Object: \u0027Object Repository/Page_BugsUI Edit Product/button_AddNewRow_Component\u0027 is clicked on","description":"","startTime":1556785630183,"endTime":1556785630354,"childRecords":[{"testStatus":{"stackTrace":"","statusValue":"WARNING"},"type":"MESSAGE","name":"","message":"Timeout \u00270\u0027 is invalid. Using default page load timeout: \u002730\u0027","startTime":1556785630185,"endTime":0,"childRecords":[],"interuppted":false},{"testStatus":{"stackTrace":"","statusValue":"PASSED"},"type":"MESSAGE","name":"","message":"Object \u0027Object Repository/Page_BugsUI Edit Product/button_AddNewRow_Component\u0027 is present","startTime":1556785630261,"endTime":0,"childRecords":[],"interuppted":false},{"index":1,"isIgnoredIfFailed":false,"type":"TEST_STEP","name":"click","message":"Object: \u0027Object Repository/Page_BugsUI Edit Product/button_AddNewRow_Component\u0027 is clicked on","description":"","startTime":1556785630261,"endTime":1556785630353,"childRecords":[{"testStatus":{"stackTrace":"","statusValue":"PASSED"},"type":"MESSAGE","name":"","message":"Object: \u0027Object Repository/Page_BugsUI Edit Product/button_AddNewRow_Component\u0027 is clicked on","startTime":1556785630353,"endTime":0,"childRecords":[],"interuppted":false}],"interuppted":false}],"interuppted":false},{"index":2,"isIgnoredIfFailed":false,"type":"TEST_STEP","name":"setText","message":"Text \u0027C1 description\u0027 is set on object \u0027Object Repository/Page_BugsUI Edit Product/unkown_description\u0027","description":"","startTime":1556785630354,"endTime":1556785630591,"childRecords":[{"testStatus":{"stackTrace":"","statusValue":"PASSED"},"type":"MESSAGE","name":"","message":"Text \u0027C1 description\u0027 is set on object \u0027Object Repository/Page_BugsUI Edit Product/unkown_description\u0027","startTime":1556785630590,"endTime":0,"childRecords":[],"interuppted":false}],"interuppted":false},{"index":3,"isIgnoredIfFailed":false,"type":"TEST_STEP","name":"Statement - If (com.kms.katalon.core.webui.keyword.WebUiBuiltInKeywords.verifyElementPresent(com.kms.katalon.core.testobject.ObjectRepository.findTestObject(Page_BugsUI Edit Product/button_Add_component), 0))","message":"Object: \u0027Object Repository/Page_BugsUI Edit Product/button_Add_component\u0027 is clicked on","description":"","startTime":1556785630592,"endTime":1556785630702,"childRecords":[{"testStatus":{"stackTrace":"","statusValue":"WARNING"},"type":"MESSAGE","name":"","message":"Timeout \u00270\u0027 is invalid. Using default page load timeout: \u002730\u0027","startTime":1556785630597,"endTime":0,"childRecords":[],"interuppted":false},{"testStatus":{"stackTrace":"","statusValue":"PASSED"},"type":"MESSAGE","name":"","message":"Object \u0027Object Repository/Page_BugsUI Edit Product/button_Add_component\u0027 is present","startTime":1556785630617,"endTime":0,"childRecords":[],"interuppted":false},{"index":1,"isIgnoredIfFailed":false,"type":"TEST_STEP","name":"click","message":"Object: \u0027Object Repository/Page_BugsUI Edit Product/button_Add_component\u0027 is clicked on","description":"","startTime":1556785630618,"endTime":1556785630701,"childRecords":[{"testStatus":{"stackTrace":"","statusValue":"PASSED"},"type":"MESSAGE","name":"","message":"Object: \u0027Object Repository/Page_BugsUI Edit Product/button_Add_component\u0027 is clicked on","startTime":1556785630701,"endTime":0,"childRecords":[],"interuppted":false}],"interuppted":false}],"interuppted":false},{"index":4,"isIgnoredIfFailed":false,"type":"TEST_STEP","name":"Statement - If (com.kms.katalon.core.webui.keyword.WebUiBuiltInKeywords.verifyElementPresent(com.kms.katalon.core.testobject.ObjectRepository.findTestObject(Page_BugsUI Edit Product/div_Name_Email_required), 0))","description":"","startTime":1556785630702,"endTime":1556785631854,"childRecords":[{"testStatus":{"stackTrace":"","statusValue":"WARNING"},"type":"MESSAGE","name":"","message":"Timeout \u00270\u0027 is invalid. Using default page load timeout: \u002730\u0027","startTime":1556785630708,"endTime":0,"childRecords":[],"interuppted":false},{"testStatus":{"stackTrace":"","statusValue":"PASSED"},"type":"MESSAGE","name":"","message":"Object \u0027Object Repository/Page_BugsUI Edit Product/div_Name_Email_required\u0027 is present","startTime":1556785631796,"endTime":0,"childRecords":[],"interuppted":false},{"index":1,"isIgnoredIfFailed":false,"type":"TEST_STEP","name":"Statement - componentNameEmailReqMsg \u003d com.kms.katalon.core.webui.keyword.WebUiBuiltInKeywords.getText(com.kms.katalon.core.testobject.ObjectRepository.findTestObject(Page_BugsUI Edit Product/div_Name_Email_required))","message":"Text of object \u0027Object Repository/Page_BugsUI Edit Product/div_Name_Email_required\u0027 is: \u0027Name is required, Email is required\u0027","description":"","startTime":1556785631796,"endTime":1556785631852,"childRecords":[{"testStatus":{"stackTrace":"","statusValue":"PASSED"},"type":"MESSAGE","name":"","message":"Text of object \u0027Object Repository/Page_BugsUI Edit Product/div_Name_Email_required\u0027 is: \u0027Name is required, Email is required\u0027","startTime":1556785631851,"endTime":0,"childRecords":[],"interuppted":false}],"interuppted":false},{"index":2,"isIgnoredIfFailed":false,"type":"TEST_STEP","name":"Statement - If (componentNameEmailReqMsg.equals(\"Name is required, Email is required\"))","description":"","startTime":1556785631852,"endTime":1556785631853,"childRecords":[{"index":1,"isIgnoredIfFailed":false,"type":"TEST_STEP","name":"Statement - assert true","description":"","startTime":1556785631853,"endTime":1556785631853,"childRecords":[],"interuppted":false}],"interuppted":false}],"interuppted":false},{"index":5,"isIgnoredIfFailed":false,"type":"TEST_STEP","name":"delay","message":"Delayed 2 second(s)","description":"","startTime":1556785631854,"endTime":1556785633856,"childRecords":[{"testStatus":{"stackTrace":"","statusValue":"PASSED"},"type":"MESSAGE","name":"","message":"Delayed 2 second(s)","startTime":1556785633854,"endTime":0,"childRecords":[],"interuppted":false}],"interuppted":false},{"index":6,"isIgnoredIfFailed":false,"type":"TEST_STEP","name":"setText","message":"Text \u0027C1 desc\u0027 is set on object \u0027Object Repository/Page_BugsUI Edit Product/unkown_description\u0027","description":"","startTime":1556785633857,"endTime":1556785634055,"childRecords":[{"testStatus":{"stackTrace":"","statusValue":"PASSED"},"type":"MESSAGE","name":"","message":"Text \u0027C1 desc\u0027 is set on object \u0027Object Repository/Page_BugsUI Edit Product/unkown_description\u0027","startTime":1556785634054,"endTime":0,"childRecords":[],"interuppted":false}],"interuppted":false},{"index":7,"isIgnoredIfFailed":false,"type":"TEST_STEP","name":"click","message":"Object: \u0027Object Repository/Page_BugsUI Edit Product/button_Add_component\u0027 is clicked on","description":"","startTime":1556785634055,"endTime":1556785634149,"childRecords":[{"testStatus":{"stackTrace":"","statusValue":"PASSED"},"type":"MESSAGE","name":"","message":"Object: \u0027Object Repository/Page_BugsUI Edit Product/button_Add_component\u0027 is clicked on","startTime":1556785634149,"endTime":0,"childRecords":[],"interuppted":false}],"interuppted":false},{"index":8,"isIgnoredIfFailed":false,"type":"TEST_STEP","name":"delay","message":"Delayed 2 second(s)","description":"","startTime":1556785634149,"endTime":1556785636153,"childRecords":[{"testStatus":{"stackTrace":"","statusValue":"PASSED"},"type":"MESSAGE","name":"","message":"Delayed 2 second(s)","startTime":1556785636152,"endTime":0,"childRecords":[],"interuppted":false}],"interuppted":false},{"index":9,"isIgnoredIfFailed":false,"type":"TEST_STEP","name":"setText","message":"Text \u0027C1\u0027 is set on object \u0027Object Repository/Page_BugsUI Edit Product/unknown_Component\u0027","description":"","startTime":1556785636153,"endTime":1556785636335,"childRecords":[{"testStatus":{"stackTrace":"","statusValue":"PASSED"},"type":"MESSAGE","name":"","message":"Text \u0027C1\u0027 is set on object \u0027Object Repository/Page_BugsUI Edit Product/unknown_Component\u0027","startTime":1556785636335,"endTime":0,"childRecords":[],"interuppted":false}],"interuppted":false},{"index":10,"isIgnoredIfFailed":false,"type":"TEST_STEP","name":"setText","message":"Text \u0027kumar.nagendra@happiestminds.com\u0027 is set on object \u0027Object Repository/Page_BugsUI Edit Product/unkown_defaultAssignee\u0027","description":"","startTime":1556785636336,"endTime":1556785636713,"childRecords":[{"testStatus":{"stackTrace":"","statusValue":"PASSED"},"type":"MESSAGE","name":"","message":"Text \u0027kumar.nagendra@happiestminds.com\u0027 is set on object \u0027Object Repository/Page_BugsUI Edit Product/unkown_defaultAssignee\u0027","startTime":1556785636712,"endTime":0,"childRecords":[],"interuppted":false}],"interuppted":false},{"index":11,"isIgnoredIfFailed":false,"type":"TEST_STEP","name":"Statement - If (com.kms.katalon.core.webui.keyword.WebUiBuiltInKeywords.verifyElementPresent(com.kms.katalon.core.testobject.ObjectRepository.findTestObject(Page_BugsUI Edit Product/button_Add_component), 0))","message":"Object: \u0027Object Repository/Page_BugsUI Edit Product/button_Add_component\u0027 is clicked on","description":"","startTime":1556785636713,"endTime":1556785636822,"childRecords":[{"testStatus":{"stackTrace":"","statusValue":"WARNING"},"type":"MESSAGE","name":"","message":"Timeout \u00270\u0027 is invalid. Using default page load timeout: \u002730\u0027","startTime":1556785636718,"endTime":0,"childRecords":[],"interuppted":false},{"testStatus":{"stackTrace":"","statusValue":"PASSED"},"type":"MESSAGE","name":"","message":"Object \u0027Object Repository/Page_BugsUI Edit Product/button_Add_component\u0027 is present","startTime":1556785636733,"endTime":0,"childRecords":[],"interuppted":false},{"index":1,"isIgnoredIfFailed":false,"type":"TEST_STEP","name":"click","message":"Object: \u0027Object Repository/Page_BugsUI Edit Product/button_Add_component\u0027 is clicked on","description":"","startTime":1556785636733,"endTime":1556785636822,"childRecords":[{"testStatus":{"stackTrace":"","statusValue":"PASSED"},"type":"MESSAGE","name":"","message":"Object: \u0027Object Repository/Page_BugsUI Edit Product/button_Add_component\u0027 is clicked on","startTime":1556785636822,"endTime":0,"childRecords":[],"interuppted":false}],"interuppted":false}],"interuppted":false},{"index":12,"isIgnoredIfFailed":false,"type":"TEST_STEP","name":"Statement - If (com.kms.katalon.core.webui.keyword.WebUiBuiltInKeywords.verifyElementPresent(com.kms.katalon.core.testobject.ObjectRepository.findTestObject(Page_BugsUI Edit Product/div_Component_added), 0))","description":"","startTime":1556785636823,"endTime":1556785637962,"childRecords":[{"testStatus":{"stackTrace":"","statusValue":"WARNING"},"type":"MESSAGE","name":"","message":"Timeout \u00270\u0027 is invalid. Using default page load timeout: \u002730\u0027","startTime":1556785636828,"endTime":0,"childRecords":[],"interuppted":false},{"testStatus":{"stackTrace":"","statusValue":"PASSED"},"type":"MESSAGE","name":"","message":"Object \u0027Object Repository/Page_BugsUI Edit Product/div_Component_added\u0027 is present","startTime":1556785637911,"endTime":0,"childRecords":[],"interuppted":false},{"index":1,"isIgnoredIfFailed":false,"type":"TEST_STEP","name":"Statement - componentAddedSuccessMsg \u003d com.kms.katalon.core.webui.keyword.WebUiBuiltInKeywords.getText(com.kms.katalon.core.testobject.ObjectRepository.findTestObject(Page_BugsUI Edit Product/div_Component_added))","message":"Text of object \u0027Object Repository/Page_BugsUI Edit Product/div_Component_added\u0027 is: \u0027Component has been added successfully.\u0027","description":"","startTime":1556785637912,"endTime":1556785637961,"childRecords":[{"testStatus":{"stackTrace":"","statusValue":"PASSED"},"type":"MESSAGE","name":"","message":"Text of object \u0027Object Repository/Page_BugsUI Edit Product/div_Component_added\u0027 is: \u0027Component has been added successfully.\u0027","startTime":1556785637959,"endTime":0,"childRecords":[],"interuppted":false}],"interuppted":false},{"index":2,"isIgnoredIfFailed":false,"type":"TEST_STEP","name":"Statement - If (componentAddedSuccessMsg.equals(\"Component has been added successfully.\"))","description":"","startTime":1556785637961,"endTime":1556785637962,"childRecords":[{"index":1,"isIgnoredIfFailed":false,"type":"TEST_STEP","name":"Statement - assert true","description":"","startTime":1556785637961,"endTime":1556785637962,"childRecords":[],"interuppted":false}],"interuppted":false}],"interuppted":false},{"index":13,"isIgnoredIfFailed":false,"type":"TEST_STEP","name":"delay","message":"Delayed 3 second(s)","description":"","startTime":1556785637962,"endTime":1556785640963,"childRecords":[{"testStatus":{"stackTrace":"","statusValue":"PASSED"},"type":"MESSAGE","name":"","message":"Delayed 3 second(s)","startTime":1556785640963,"endTime":0,"childRecords":[],"interuppted":false}],"interuppted":false},{"index":14,"isIgnoredIfFailed":false,"type":"TEST_STEP","name":"Statement - compName \u003d com.kms.katalon.core.webui.keyword.WebUiBuiltInKeywords.getAttribute(com.kms.katalon.core.testobject.ObjectRepository.findTestObject(Page_BugsUI Edit Product/unknown_Component), \"value\")","message":"Attribute \u0027value\u0027 of object \u0027Object Repository/Page_BugsUI Edit Product/unknown_Component\u0027 is: \u0027C1\u0027","description":"","startTime":1556785640964,"endTime":1556785641009,"childRecords":[{"testStatus":{"stackTrace":"","statusValue":"PASSED"},"type":"MESSAGE","name":"","message":"Attribute \u0027value\u0027 of object \u0027Object Repository/Page_BugsUI Edit Product/unknown_Component\u0027 is: \u0027C1\u0027","startTime":1556785641009,"endTime":0,"childRecords":[],"interuppted":false}],"interuppted":false},{"index":15,"isIgnoredIfFailed":false,"type":"TEST_STEP","name":"Statement - If (compName.equals(\"C1\"))","description":"","startTime":1556785641009,"endTime":1556785641009,"childRecords":[{"index":1,"isIgnoredIfFailed":false,"type":"TEST_STEP","name":"Statement - assert true","description":"","startTime":1556785641009,"endTime":1556785641009,"childRecords":[],"interuppted":false}],"interuppted":false},{"index":17,"isIgnoredIfFailed":false,"type":"TEST_STEP","name":"delay","message":"Delayed 3 second(s)","description":"","startTime":1556785641009,"endTime":1556785644012,"childRecords":[{"testStatus":{"stackTrace":"","statusValue":"PASSED"},"type":"MESSAGE","name":"","message":"Delayed 3 second(s)","startTime":1556785644010,"endTime":0,"childRecords":[],"interuppted":false}],"interuppted":false},{"index":18,"isIgnoredIfFailed":false,"type":"TEST_STEP","name":"Statement - If (com.kms.katalon.core.webui.keyword.WebUiBuiltInKeywords.verifyElementPresent(com.kms.katalon.core.testobject.ObjectRepository.findTestObject(Page_BugsUI Edit Product/delete_icon_unknownCompnent), 0))","message":"Object: \u0027Object Repository/Page_BugsUI Edit Product/delete_icon_unknownCompnent\u0027 is clicked on","description":"","startTime":1556785644013,"endTime":1556785644192,"childRecords":[{"testStatus":{"stackTrace":"","statusValue":"WARNING"},"type":"MESSAGE","name":"","message":"Timeout \u00270\u0027 is invalid. Using default page load timeout: \u002730\u0027","startTime":1556785644025,"endTime":0,"childRecords":[],"interuppted":false},{"testStatus":{"stackTrace":"","statusValue":"PASSED"},"type":"MESSAGE","name":"","message":"Object \u0027Object Repository/Page_BugsUI Edit Product/delete_icon_unknownCompnent\u0027 is present","startTime":1556785644087,"endTime":0,"childRecords":[],"interuppted":false},{"index":1,"isIgnoredIfFailed":false,"type":"TEST_STEP","name":"click","message":"Object: \u0027Object Repository/Page_BugsUI Edit Product/delete_icon_unknownCompnent\u0027 is clicked on","description":"","startTime":1556785644087,"endTime":1556785644191,"childRecords":[{"testStatus":{"stackTrace":"","statusValue":"PASSED"},"type":"MESSAGE","name":"","message":"Object: \u0027Object Repository/Page_BugsUI Edit Product/delete_icon_unknownCompnent\u0027 is clicked on","startTime":1556785644190,"endTime":0,"childRecords":[],"interuppted":false}],"interuppted":false}],"interuppted":false},{"index":19,"isIgnoredIfFailed":false,"type":"TEST_STEP","name":"reusable.editPage.deleteComponent","message":"reusable.editPage.deleteComponent is PASSED","description":"","startTime":1556785644193,"endTime":1556785644368,"childRecords":[{"testStatus":{"stackTrace":"","statusValue":"WARNING"},"type":"MESSAGE","name":"","message":"Timeout \u00270\u0027 is invalid. Using default page load timeout: \u002730\u0027","startTime":1556785644198,"endTime":0,"childRecords":[],"interuppted":false},{"testStatus":{"stackTrace":"","statusValue":"PASSED"},"type":"MESSAGE","name":"","message":"Object \u0027Object Repository/Page_BugsUI Edit Product/confirmDeleteProduct_popup\u0027 is present","startTime":1556785644232,"endTime":0,"childRecords":[],"interuppted":false},{"testStatus":{"stackTrace":"","statusValue":"WARNING"},"type":"MESSAGE","name":"","message":"Timeout \u00270\u0027 is invalid. Using default page load timeout: \u002730\u0027","startTime":1556785644236,"endTime":0,"childRecords":[],"interuppted":false},{"testStatus":{"stackTrace":"","statusValue":"PASSED"},"type":"MESSAGE","name":"","message":"Object \u0027Object Repository/Page_BugsUI Edit Product/button_component_Yes\u0027 is present","startTime":1556785644258,"endTime":0,"childRecords":[],"interuppted":false},{"testStatus":{"stackTrace":"","statusValue":"PASSED"},"type":"MESSAGE","name":"","message":"Object: \u0027Object Repository/Page_BugsUI Edit Product/button_component_Yes\u0027 is clicked on","startTime":1556785644366,"endTime":0,"childRecords":[],"interuppted":false},{"testStatus":{"stackTrace":"","statusValue":"PASSED"},"type":"MESSAGE","name":"","message":"reusable.editPage.deleteComponent is PASSED","startTime":1556785644367,"endTime":0,"childRecords":[],"interuppted":false}],"interuppted":false},{"index":20,"isIgnoredIfFailed":false,"type":"TEST_STEP","name":"Statement - If (com.kms.katalon.core.webui.keyword.WebUiBuiltInKeywords.verifyElementPresent(com.kms.katalon.core.testobject.ObjectRepository.findTestObject(Page_BugsUI Edit Product/div_Component_deleted), 0))","description":"","startTime":1556785644368,"endTime":1556785645486,"childRecords":[{"testStatus":{"stackTrace":"","statusValue":"WARNING"},"type":"MESSAGE","name":"","message":"Timeout \u00270\u0027 is invalid. Using default page load timeout: \u002730\u0027","startTime":1556785644373,"endTime":0,"childRecords":[],"interuppted":false},{"testStatus":{"stackTrace":"","statusValue":"PASSED"},"type":"MESSAGE","name":"","message":"Object \u0027Object Repository/Page_BugsUI Edit Product/div_Component_deleted\u0027 is present","startTime":1556785645449,"endTime":0,"childRecords":[],"interuppted":false},{"index":1,"isIgnoredIfFailed":false,"type":"TEST_STEP","name":"Statement - componentDeletedSuccessMsg \u003d com.kms.katalon.core.webui.keyword.WebUiBuiltInKeywords.getText(com.kms.katalon.core.testobject.ObjectRepository.findTestObject(Page_BugsUI Edit Product/div_Component_deleted))","message":"Text of object \u0027Object Repository/Page_BugsUI Edit Product/div_Component_deleted\u0027 is: \u0027Component has been deleted successfully.\u0027","description":"","startTime":1556785645450,"endTime":1556785645484,"childRecords":[{"testStatus":{"stackTrace":"","statusValue":"PASSED"},"type":"MESSAGE","name":"","message":"Text of object \u0027Object Repository/Page_BugsUI Edit Product/div_Component_deleted\u0027 is: \u0027Component has been deleted successfully.\u0027","startTime":1556785645484,"endTime":0,"childRecords":[],"interuppted":false}],"interuppted":false},{"index":2,"isIgnoredIfFailed":false,"type":"TEST_STEP","name":"Statement - If (componentDeletedSuccessMsg.equals(\"Component has been deleted successfully.\"))","description":"","startTime":1556785645484,"endTime":1556785645485,"childRecords":[{"index":1,"isIgnoredIfFailed":false,"type":"TEST_STEP","name":"Statement - assert true","description":"","startTime":1556785645485,"endTime":1556785645485,"childRecords":[],"interuppted":false}],"interuppted":false}],"interuppted":false},{"index":21,"isIgnoredIfFailed":false,"type":"TEST_STEP","name":"delay","message":"Delayed 2 second(s)","description":"","startTime":1556785645486,"endTime":1556785647488,"childRecords":[{"testStatus":{"stackTrace":"","statusValue":"PASSED"},"type":"MESSAGE","name":"","message":"Delayed 2 second(s)","startTime":1556785647487,"endTime":0,"childRecords":[],"interuppted":false}],"interuppted":false},{"index":22,"isIgnoredIfFailed":false,"type":"TEST_STEP","name":"Statement - If (!(com.kms.katalon.core.webui.keyword.WebUiBuiltInKeywords.getAttribute(com.kms.katalon.core.testobject.ObjectRepository.findTestObject(Page_BugsUI Edit Product/unknown_Component), \"value\").equals(\"C1\")))","description":"","startTime":1556785647489,"endTime":1556785647574,"childRecords":[{"testStatus":{"stackTrace":"","statusValue":"PASSED"},"type":"MESSAGE","name":"","message":"Attribute \u0027value\u0027 of object \u0027Object Repository/Page_BugsUI Edit Product/unknown_Component\u0027 is: \u0027Unknown\u0027","startTime":1556785647574,"endTime":0,"childRecords":[],"interuppted":false},{"index":1,"isIgnoredIfFailed":false,"type":"TEST_STEP","name":"Statement - assert true","description":"","startTime":1556785647574,"endTime":1556785647574,"childRecords":[],"interuppted":false}],"interuppted":false},{"index":24,"isIgnoredIfFailed":false,"type":"TEST_STEP","name":"delay","message":"Delayed 3 second(s)","description":"","startTime":1556785647574,"endTime":1556785650576,"childRecords":[{"testStatus":{"stackTrace":"","statusValue":"PASSED"},"type":"MESSAGE","name":"","message":"Delayed 3 second(s)","startTime":1556785650574,"endTime":0,"childRecords":[],"interuppted":false}],"interuppted":false},{"testStatus":{"stackTrace":"","statusValue":"PASSED"},"type":"MESSAGE","name":"","message":"Test Cases/Edit_Product/component_section","startTime":1556785650577,"endTime":0,"childRecords":[],"interuppted":false}],"interuppted":false},{"isOptional":false,"type":"TEST_CASE","name":"Test Cases/Edit_Product/version_section","id":"Test Cases/Edit_Product/version_section","source":"C:\\\\New-Bugzilla-Application\\\\New_Bugzilla-UI-V2\\\\Test Cases\\\\Edit_Product\\\\version_section.tc","message":"Test Cases/Edit_Product/version_section","description":"","startTime":1556785650589,"endTime":1556785668014,"childRecords":[{"testStatus":{"stackTrace":"","statusValue":"INFO"},"type":"MESSAGE","name":"","message":"Evaluating variables for test case","startTime":1556785650617,"endTime":0,"childRecords":[],"interuppted":false},{"index":1,"isIgnoredIfFailed":false,"type":"TEST_STEP","name":"Statement - If (com.kms.katalon.core.webui.keyword.WebUiBuiltInKeywords.verifyElementPresent(com.kms.katalon.core.testobject.ObjectRepository.findTestObject(Page_BugsUI Edit Product/delete_icon_version), 0))","message":"Object: \u0027Object Repository/Page_BugsUI Edit Product/delete_icon_version\u0027 is clicked on","description":"","startTime":1556785650868,"endTime":1556785651007,"childRecords":[{"testStatus":{"stackTrace":"","statusValue":"WARNING"},"type":"MESSAGE","name":"","message":"Timeout \u00270\u0027 is invalid. Using default page load timeout: \u002730\u0027","startTime":1556785650871,"endTime":0,"childRecords":[],"interuppted":false},{"testStatus":{"stackTrace":"","statusValue":"PASSED"},"type":"MESSAGE","name":"","message":"Object \u0027Object Repository/Page_BugsUI Edit Product/delete_icon_version\u0027 is present","startTime":1556785650900,"endTime":0,"childRecords":[],"interuppted":false},{"index":1,"isIgnoredIfFailed":false,"type":"TEST_STEP","name":"click","message":"Object: \u0027Object Repository/Page_BugsUI Edit Product/delete_icon_version\u0027 is clicked on","description":"","startTime":1556785650900,"endTime":1556785651006,"childRecords":[{"testStatus":{"stackTrace":"","statusValue":"PASSED"},"type":"MESSAGE","name":"","message":"Object: \u0027Object Repository/Page_BugsUI Edit Product/delete_icon_version\u0027 is clicked on","startTime":1556785651005,"endTime":0,"childRecords":[],"interuppted":false}],"interuppted":false}],"interuppted":false},{"index":2,"isIgnoredIfFailed":false,"type":"TEST_STEP","name":"delay","message":"Delayed 2 second(s)","description":"","startTime":1556785651008,"endTime":1556785653012,"childRecords":[{"testStatus":{"stackTrace":"","statusValue":"PASSED"},"type":"MESSAGE","name":"","message":"Delayed 2 second(s)","startTime":1556785653011,"endTime":0,"childRecords":[],"interuppted":false}],"interuppted":false},{"index":3,"isIgnoredIfFailed":false,"type":"TEST_STEP","name":"Statement - If (com.kms.katalon.core.webui.keyword.WebUiBuiltInKeywords.verifyElementPresent(com.kms.katalon.core.testobject.ObjectRepository.findTestObject(Page_BugsUI Edit Product/confirmDeleteProduct_popup), 0))","message":"Object: \u0027Object Repository/Page_BugsUI Edit Product/button_version_Yes\u0027 is clicked on","description":"","startTime":1556785653013,"endTime":1556785653175,"childRecords":[{"testStatus":{"stackTrace":"","statusValue":"WARNING"},"type":"MESSAGE","name":"","message":"Timeout \u00270\u0027 is invalid. Using default page load timeout: \u002730\u0027","startTime":1556785653021,"endTime":0,"childRecords":[],"interuppted":false},{"testStatus":{"stackTrace":"","statusValue":"PASSED"},"type":"MESSAGE","name":"","message":"Object \u0027Object Repository/Page_BugsUI Edit Product/confirmDeleteProduct_popup\u0027 is present","startTime":1556785653063,"endTime":0,"childRecords":[],"interuppted":false},{"index":1,"isIgnoredIfFailed":false,"type":"TEST_STEP","name":"Statement - If (com.kms.katalon.core.webui.keyword.WebUiBuiltInKeywords.verifyElementPresent(com.kms.katalon.core.testobject.ObjectRepository.findTestObject(Page_BugsUI Edit Product/button_version_Yes), 0))","message":"Object: \u0027Object Repository/Page_BugsUI Edit Product/button_version_Yes\u0027 is clicked on","description":"","startTime":1556785653063,"endTime":1556785653175,"childRecords":[{"testStatus":{"stackTrace":"","statusValue":"WARNING"},"type":"MESSAGE","name":"","message":"Timeout \u00270\u0027 is invalid. Using default page load timeout: \u002730\u0027","startTime":1556785653063,"endTime":0,"childRecords":[],"interuppted":false},{"testStatus":{"stackTrace":"","statusValue":"PASSED"},"type":"MESSAGE","name":"","message":"Object \u0027Object Repository/Page_BugsUI Edit Product/button_version_Yes\u0027 is present","startTime":1556785653097,"endTime":0,"childRecords":[],"interuppted":false},{"index":1,"isIgnoredIfFailed":false,"type":"TEST_STEP","name":"click","message":"Object: \u0027Object Repository/Page_BugsUI Edit Product/button_version_Yes\u0027 is clicked on","description":"","startTime":1556785653097,"endTime":1556785653174,"childRecords":[{"testStatus":{"stackTrace":"","statusValue":"PASSED"},"type":"MESSAGE","name":"","message":"Object: \u0027Object Repository/Page_BugsUI Edit Product/button_version_Yes\u0027 is clicked on","startTime":1556785653174,"endTime":0,"childRecords":[],"interuppted":false}],"interuppted":false}],"interuppted":false}],"interuppted":false},{"index":4,"isIgnoredIfFailed":false,"type":"TEST_STEP","name":"delay","message":"Delayed 2 second(s)","description":"","startTime":1556785653175,"endTime":1556785655177,"childRecords":[{"testStatus":{"stackTrace":"","statusValue":"PASSED"},"type":"MESSAGE","name":"","message":"Delayed 2 second(s)","startTime":1556785655176,"endTime":0,"childRecords":[],"interuppted":false}],"interuppted":false},{"index":5,"isIgnoredIfFailed":false,"type":"TEST_STEP","name":"Statement - If (com.kms.katalon.core.webui.keyword.WebUiBuiltInKeywords.verifyElementPresent(com.kms.katalon.core.testobject.ObjectRepository.findTestObject(Page_BugsUI Edit Product/div_Product_atleast_1_version), 0))","description":"","startTime":1556785655178,"endTime":1556785655296,"childRecords":[{"testStatus":{"stackTrace":"","statusValue":"WARNING"},"type":"MESSAGE","name":"","message":"Timeout \u00270\u0027 is invalid. Using default page load timeout: \u002730\u0027","startTime":1556785655200,"endTime":0,"childRecords":[],"interuppted":false},{"testStatus":{"stackTrace":"","statusValue":"PASSED"},"type":"MESSAGE","name":"","message":"Object \u0027Object Repository/Page_BugsUI Edit Product/div_Product_atleast_1_version\u0027 is present","startTime":1556785655255,"endTime":0,"childRecords":[],"interuppted":false},{"index":1,"isIgnoredIfFailed":false,"type":"TEST_STEP","name":"Statement - warningMessage \u003d com.kms.katalon.core.webui.keyword.WebUiBuiltInKeywords.getText(com.kms.katalon.core.testobject.ObjectRepository.findTestObject(Page_BugsUI Edit Product/div_Product_atleast_1_version))","message":"Text of object \u0027Object Repository/Page_BugsUI Edit Product/div_Product_atleast_1_version\u0027 is: \u0027Product must have atleast 1 version.\u0027","description":"","startTime":1556785655255,"endTime":1556785655291,"childRecords":[{"testStatus":{"stackTrace":"","statusValue":"PASSED"},"type":"MESSAGE","name":"","message":"Text of object \u0027Object Repository/Page_BugsUI Edit Product/div_Product_atleast_1_version\u0027 is: \u0027Product must have atleast 1 version.\u0027","startTime":1556785655291,"endTime":0,"childRecords":[],"interuppted":false}],"interuppted":false},{"index":2,"isIgnoredIfFailed":false,"type":"TEST_STEP","name":"Statement - If (warningMessage.equals(\"Product must have atleast 1 version.\"))","description":"","startTime":1556785655291,"endTime":1556785655296,"childRecords":[{"index":1,"isIgnoredIfFailed":false,"type":"TEST_STEP","name":"Statement - assert true","description":"","startTime":1556785655291,"endTime":1556785655296,"childRecords":[],"interuppted":false}],"interuppted":false}],"interuppted":false},{"index":6,"isIgnoredIfFailed":false,"type":"TEST_STEP","name":"delay","message":"Delayed 3 second(s)","description":"","startTime":1556785655296,"endTime":1556785658298,"childRecords":[{"testStatus":{"stackTrace":"","statusValue":"PASSED"},"type":"MESSAGE","name":"","message":"Delayed 3 second(s)","startTime":1556785658298,"endTime":0,"childRecords":[],"interuppted":false}],"interuppted":false},{"index":7,"isIgnoredIfFailed":false,"type":"TEST_STEP","name":"Statement - If (com.kms.katalon.core.webui.keyword.WebUiBuiltInKeywords.verifyElementPresent(com.kms.katalon.core.testobject.ObjectRepository.findTestObject(Page_BugsUI Edit Product/update_icon_version), 0))","description":"","startTime":1556785658299,"endTime":1556785658519,"childRecords":[{"testStatus":{"stackTrace":"","statusValue":"WARNING"},"type":"MESSAGE","name":"","message":"Timeout \u00270\u0027 is invalid. Using default page load timeout: \u002730\u0027","startTime":1556785658302,"endTime":0,"childRecords":[],"interuppted":false},{"testStatus":{"stackTrace":"","statusValue":"PASSED"},"type":"MESSAGE","name":"","message":"Object \u0027Object Repository/Page_BugsUI Edit Product/update_icon_version\u0027 is present","startTime":1556785658332,"endTime":0,"childRecords":[],"interuppted":false},{"index":1,"isIgnoredIfFailed":false,"type":"TEST_STEP","name":"click","message":"Object: \u0027Object Repository/Page_BugsUI Edit Product/update_icon_version\u0027 is clicked on","description":"","startTime":1556785658332,"endTime":1556785658438,"childRecords":[{"testStatus":{"stackTrace":"","statusValue":"PASSED"},"type":"MESSAGE","name":"","message":"Object: \u0027Object Repository/Page_BugsUI Edit Product/update_icon_version\u0027 is clicked on","startTime":1556785658437,"endTime":0,"childRecords":[],"interuppted":false}],"interuppted":false},{"index":2,"isIgnoredIfFailed":false,"type":"TEST_STEP","name":"Statement - If (com.kms.katalon.core.webui.keyword.WebUiBuiltInKeywords.verifyElementPresent(com.kms.katalon.core.testobject.ObjectRepository.findTestObject(Page_BugsUI Edit Product/div_Nothing to update), 0))","description":"","startTime":1556785658438,"endTime":1556785658519,"childRecords":[{"testStatus":{"stackTrace":"","statusValue":"WARNING"},"type":"MESSAGE","name":"","message":"Timeout \u00270\u0027 is invalid. Using default page load timeout: \u002730\u0027","startTime":1556785658443,"endTime":0,"childRecords":[],"interuppted":false},{"testStatus":{"stackTrace":"","statusValue":"PASSED"},"type":"MESSAGE","name":"","message":"Object \u0027Object Repository/Page_BugsUI Edit Product/div_Nothing to update\u0027 is present","startTime":1556785658468,"endTime":0,"childRecords":[],"interuppted":false},{"index":1,"isIgnoredIfFailed":false,"type":"TEST_STEP","name":"Statement - nothingToUpdate \u003d com.kms.katalon.core.webui.keyword.WebUiBuiltInKeywords.getText(com.kms.katalon.core.testobject.ObjectRepository.findTestObject(Page_BugsUI Edit Product/div_Nothing to update))","message":"Text of object \u0027Object Repository/Page_BugsUI Edit Product/div_Nothing to update\u0027 is: \u0027Nothing to update.\u0027","description":"","startTime":1556785658468,"endTime":1556785658517,"childRecords":[{"testStatus":{"stackTrace":"","statusValue":"PASSED"},"type":"MESSAGE","name":"","message":"Text of object \u0027Object Repository/Page_BugsUI Edit Product/div_Nothing to update\u0027 is: \u0027Nothing to update.\u0027","startTime":1556785658516,"endTime":0,"childRecords":[],"interuppted":false}],"interuppted":false},{"index":2,"isIgnoredIfFailed":false,"type":"TEST_STEP","name":"Statement - If (nothingToUpdate.equals(\"Nothing to update.\"))","description":"","startTime":1556785658517,"endTime":1556785658519,"childRecords":[{"index":1,"isIgnoredIfFailed":false,"type":"TEST_STEP","name":"Statement - assert true","description":"","startTime":1556785658518,"endTime":1556785658518,"childRecords":[],"interuppted":false}],"interuppted":false}],"interuppted":false}],"interuppted":false},{"index":8,"isIgnoredIfFailed":false,"type":"TEST_STEP","name":"Statement - If (com.kms.katalon.core.webui.keyword.WebUiBuiltInKeywords.verifyElementPresent(com.kms.katalon.core.testobject.ObjectRepository.findTestObject(Page_BugsUI Edit Product/button_AddNewRow_version), 0))","message":"Object: \u0027Object Repository/Page_BugsUI Edit Product/button_AddNewRow_version\u0027 is clicked on","description":"","startTime":1556785658519,"endTime":1556785658620,"childRecords":[{"testStatus":{"stackTrace":"","statusValue":"WARNING"},"type":"MESSAGE","name":"","message":"Timeout \u00270\u0027 is invalid. Using default page load timeout: \u002730\u0027","startTime":1556785658523,"endTime":0,"childRecords":[],"interuppted":false},{"testStatus":{"stackTrace":"","statusValue":"PASSED"},"type":"MESSAGE","name":"","message":"Object \u0027Object Repository/Page_BugsUI Edit Product/button_AddNewRow_version\u0027 is present","startTime":1556785658540,"endTime":0,"childRecords":[],"interuppted":false},{"index":1,"isIgnoredIfFailed":false,"type":"TEST_STEP","name":"click","message":"Object: \u0027Object Repository/Page_BugsUI Edit Product/button_AddNewRow_version\u0027 is clicked on","description":"","startTime":1556785658540,"endTime":1556785658620,"childRecords":[{"testStatus":{"stackTrace":"","statusValue":"PASSED"},"type":"MESSAGE","name":"","message":"Object: \u0027Object Repository/Page_BugsUI Edit Product/button_AddNewRow_version\u0027 is clicked on","startTime":1556785658619,"endTime":0,"childRecords":[],"interuppted":false}],"interuppted":false}],"interuppted":false},{"index":9,"isIgnoredIfFailed":false,"type":"TEST_STEP","name":"setText","message":"Text \u0027V7\u0027 is set on object \u0027Object Repository/Page_BugsUI Edit Product/input_versionName\u0027","description":"","startTime":1556785658620,"endTime":1556785658759,"childRecords":[{"testStatus":{"stackTrace":"","statusValue":"PASSED"},"type":"MESSAGE","name":"","message":"Text \u0027V7\u0027 is set on object \u0027Object Repository/Page_BugsUI Edit Product/input_versionName\u0027","startTime":1556785658759,"endTime":0,"childRecords":[],"interuppted":false}],"interuppted":false},{"index":10,"isIgnoredIfFailed":false,"type":"TEST_STEP","name":"Statement - If (com.kms.katalon.core.webui.keyword.WebUiBuiltInKeywords.verifyElementPresent(com.kms.katalon.core.testobject.ObjectRepository.findTestObject(Page_BugsUI Edit Product/button_Add_version), 0))","message":"Object: \u0027Object Repository/Page_BugsUI Edit Product/button_Add_version\u0027 is clicked on","description":"","startTime":1556785658760,"endTime":1556785658902,"childRecords":[{"testStatus":{"stackTrace":"","statusValue":"WARNING"},"type":"MESSAGE","name":"","message":"Timeout \u00270\u0027 is invalid. Using default page load timeout: \u002730\u0027","startTime":1556785658766,"endTime":0,"childRecords":[],"interuppted":false},{"testStatus":{"stackTrace":"","statusValue":"PASSED"},"type":"MESSAGE","name":"","message":"Object \u0027Object Repository/Page_BugsUI Edit Product/button_Add_version\u0027 is present","startTime":1556785658785,"endTime":0,"childRecords":[],"interuppted":false},{"index":1,"isIgnoredIfFailed":false,"type":"TEST_STEP","name":"click","message":"Object: \u0027Object Repository/Page_BugsUI Edit Product/button_Add_version\u0027 is clicked on","description":"","startTime":1556785658786,"endTime":1556785658902,"childRecords":[{"testStatus":{"stackTrace":"","statusValue":"PASSED"},"type":"MESSAGE","name":"","message":"Object: \u0027Object Repository/Page_BugsUI Edit Product/button_Add_version\u0027 is clicked on","startTime":1556785658901,"endTime":0,"childRecords":[],"interuppted":false}],"interuppted":false}],"interuppted":false},{"index":11,"isIgnoredIfFailed":false,"type":"TEST_STEP","name":"Statement - If (com.kms.katalon.core.webui.keyword.WebUiBuiltInKeywords.verifyElementPresent(com.kms.katalon.core.testobject.ObjectRepository.findTestObject(Page_BugsUI Edit Product/div_Version_added), 0))","description":"","startTime":1556785658902,"endTime":1556785659513,"childRecords":[{"testStatus":{"stackTrace":"","statusValue":"WARNING"},"type":"MESSAGE","name":"","message":"Timeout \u00270\u0027 is invalid. Using default page load timeout: \u002730\u0027","startTime":1556785658907,"endTime":0,"childRecords":[],"interuppted":false},{"testStatus":{"stackTrace":"","statusValue":"PASSED"},"type":"MESSAGE","name":"","message":"Object \u0027Object Repository/Page_BugsUI Edit Product/div_Version_added\u0027 is present","startTime":1556785659466,"endTime":0,"childRecords":[],"interuppted":false},{"index":1,"isIgnoredIfFailed":false,"type":"TEST_STEP","name":"Statement - versionAddedSuccessMsg \u003d com.kms.katalon.core.webui.keyword.WebUiBuiltInKeywords.getText(com.kms.katalon.core.testobject.ObjectRepository.findTestObject(Page_BugsUI Edit Product/div_Version_added))","message":"Text of object \u0027Object Repository/Page_BugsUI Edit Product/div_Version_added\u0027 is: \u0027Version has been added successfully.\u0027","description":"","startTime":1556785659466,"endTime":1556785659510,"childRecords":[{"testStatus":{"stackTrace":"","statusValue":"PASSED"},"type":"MESSAGE","name":"","message":"Text of object \u0027Object Repository/Page_BugsUI Edit Product/div_Version_added\u0027 is: \u0027Version has been added successfully.\u0027","startTime":1556785659509,"endTime":0,"childRecords":[],"interuppted":false}],"interuppted":false},{"index":2,"isIgnoredIfFailed":false,"type":"TEST_STEP","name":"Statement - If (versionAddedSuccessMsg.equals(\"Version has been added successfully.\"))","description":"","startTime":1556785659511,"endTime":1556785659512,"childRecords":[{"index":1,"isIgnoredIfFailed":false,"type":"TEST_STEP","name":"Statement - assert true","description":"","startTime":1556785659512,"endTime":1556785659512,"childRecords":[],"interuppted":false}],"interuppted":false}],"interuppted":false},{"index":12,"isIgnoredIfFailed":false,"type":"TEST_STEP","name":"delay","message":"Delayed 3 second(s)","description":"","startTime":1556785659513,"endTime":1556785662516,"childRecords":[{"testStatus":{"stackTrace":"","statusValue":"PASSED"},"type":"MESSAGE","name":"","message":"Delayed 3 second(s)","startTime":1556785662515,"endTime":0,"childRecords":[],"interuppted":false}],"interuppted":false},{"index":13,"isIgnoredIfFailed":false,"type":"TEST_STEP","name":"clearText","message":"Text of object \u0027Object Repository/Page_BugsUI Edit Product/input_versionName\u0027 is cleared","description":"","startTime":1556785662516,"endTime":1556785662581,"childRecords":[{"testStatus":{"stackTrace":"","statusValue":"PASSED"},"type":"MESSAGE","name":"","message":"Text of object \u0027Object Repository/Page_BugsUI Edit Product/input_versionName\u0027 is cleared","startTime":1556785662581,"endTime":0,"childRecords":[],"interuppted":false}],"interuppted":false},{"index":14,"isIgnoredIfFailed":false,"type":"TEST_STEP","name":"setText","message":"Text \u0027V5\u0027 is set on object \u0027Object Repository/Page_BugsUI Edit Product/input_versionName\u0027","description":"","startTime":1556785662582,"endTime":1556785662725,"childRecords":[{"testStatus":{"stackTrace":"","statusValue":"PASSED"},"type":"MESSAGE","name":"","message":"Text \u0027V5\u0027 is set on object \u0027Object Repository/Page_BugsUI Edit Product/input_versionName\u0027","startTime":1556785662724,"endTime":0,"childRecords":[],"interuppted":false}],"interuppted":false},{"index":15,"isIgnoredIfFailed":false,"type":"TEST_STEP","name":"click","message":"Object: \u0027Object Repository/Page_BugsUI Edit Product/update_icon_version\u0027 is clicked on","description":"","startTime":1556785662725,"endTime":1556785662823,"childRecords":[{"testStatus":{"stackTrace":"","statusValue":"PASSED"},"type":"MESSAGE","name":"","message":"Object: \u0027Object Repository/Page_BugsUI Edit Product/update_icon_version\u0027 is clicked on","startTime":1556785662822,"endTime":0,"childRecords":[],"interuppted":false}],"interuppted":false},{"index":16,"isIgnoredIfFailed":false,"type":"TEST_STEP","name":"delay","message":"Delayed 3 second(s)","description":"","startTime":1556785662823,"endTime":1556785665826,"childRecords":[{"testStatus":{"stackTrace":"","statusValue":"PASSED"},"type":"MESSAGE","name":"","message":"Delayed 3 second(s)","startTime":1556785665825,"endTime":0,"childRecords":[],"interuppted":false}],"interuppted":false},{"index":17,"isIgnoredIfFailed":false,"type":"TEST_STEP","name":"Statement - If (com.kms.katalon.core.webui.keyword.WebUiBuiltInKeywords.verifyElementPresent(com.kms.katalon.core.testobject.ObjectRepository.findTestObject(Page_BugsUI Edit Product/div_Version_updated), 0))","description":"","startTime":1556785665827,"endTime":1556785665943,"childRecords":[{"testStatus":{"stackTrace":"","statusValue":"WARNING"},"type":"MESSAGE","name":"","message":"Timeout \u00270\u0027 is invalid. Using default page load timeout: \u002730\u0027","startTime":1556785665865,"endTime":0,"childRecords":[],"interuppted":false},{"testStatus":{"stackTrace":"","statusValue":"PASSED"},"type":"MESSAGE","name":"","message":"Object \u0027Object Repository/Page_BugsUI Edit Product/div_Version_updated\u0027 is present","startTime":1556785665888,"endTime":0,"childRecords":[],"interuppted":false},{"index":1,"isIgnoredIfFailed":false,"type":"TEST_STEP","name":"Statement - versionUpdatedMsg \u003d com.kms.katalon.core.webui.keyword.WebUiBuiltInKeywords.getText(com.kms.katalon.core.testobject.ObjectRepository.findTestObject(Page_BugsUI Edit Product/div_Version_updated))","message":"Text of object \u0027Object Repository/Page_BugsUI Edit Product/div_Version_updated\u0027 is: \u0027Version has been updated successfully.\u0027","description":"","startTime":1556785665888,"endTime":1556785665943,"childRecords":[{"testStatus":{"stackTrace":"","statusValue":"PASSED"},"type":"MESSAGE","name":"","message":"Text of object \u0027Object Repository/Page_BugsUI Edit Product/div_Version_updated\u0027 is: \u0027Version has been updated successfully.\u0027","startTime":1556785665943,"endTime":0,"childRecords":[],"interuppted":false}],"interuppted":false},{"index":2,"isIgnoredIfFailed":false,"type":"TEST_STEP","name":"Statement - If (versionUpdatedMsg.equals(\"Version has been updated successfully.\"))","description":"","startTime":1556785665943,"endTime":1556785665943,"childRecords":[{"index":1,"isIgnoredIfFailed":false,"type":"TEST_STEP","name":"Statement - assert true","description":"","startTime":1556785665943,"endTime":1556785665943,"childRecords":[],"interuppted":false}],"interuppted":false}],"interuppted":false},{"index":18,"isIgnoredIfFailed":false,"type":"TEST_STEP","name":"delay","message":"Delayed 2 second(s)","description":"","startTime":1556785665943,"endTime":1556785667945,"childRecords":[{"testStatus":{"stackTrace":"","statusValue":"PASSED"},"type":"MESSAGE","name":"","message":"Delayed 2 second(s)","startTime":1556785667943,"endTime":0,"childRecords":[],"interuppted":false}],"interuppted":false},{"index":19,"isIgnoredIfFailed":false,"type":"TEST_STEP","name":"Statement - versionName \u003d com.kms.katalon.core.webui.keyword.WebUiBuiltInKeywords.getAttribute(com.kms.katalon.core.testobject.ObjectRepository.findTestObject(Page_BugsUI Edit Product/input_versionName), \"value\")","message":"Attribute \u0027value\u0027 of object \u0027Object Repository/Page_BugsUI Edit Product/input_versionName\u0027 is: \u0027V5\u0027","description":"","startTime":1556785667946,"endTime":1556785668014,"childRecords":[{"testStatus":{"stackTrace":"","statusValue":"PASSED"},"type":"MESSAGE","name":"","message":"Attribute \u0027value\u0027 of object \u0027Object Repository/Page_BugsUI Edit Product/input_versionName\u0027 is: \u0027V5\u0027","startTime":1556785668014,"endTime":0,"childRecords":[],"interuppted":false}],"interuppted":false},{"index":20,"isIgnoredIfFailed":false,"type":"TEST_STEP","name":"Statement - If (versionName.equals(\"V5\"))","description":"","startTime":1556785668014,"endTime":1556785668014,"childRecords":[{"index":1,"isIgnoredIfFailed":false,"type":"TEST_STEP","name":"Statement - assert true","description":"","startTime":1556785668014,"endTime":1556785668014,"childRecords":[],"interuppted":false}],"interuppted":false},{"testStatus":{"stackTrace":"","statusValue":"PASSED"},"type":"MESSAGE","name":"","message":"Test Cases/Edit_Product/version_section","startTime":1556785668014,"endTime":0,"childRecords":[],"interuppted":false}],"interuppted":false}],"interuppted":false}