{"devicePlatform":"","logFolder":"C:\\New-Bugzilla-Application\\New_Bugzilla-UI-V2\\Reports\\Edit_Product_Suite\\20190430_155824","runData":{"hostName":"Kumar.nagendra - HMECL001948.happiestminds.com","os":"Windows 10 64bit","katalonVersion":"5.3.0.1","browser":"Chrome 73.0.3683.103","hostAddress":"10.95.75.221","sessionId":"37b08e34c1c236490892a02c73ee9e8c","seleniumVersion":"3.7.1","proxyInformation":"ProxyInformation{proxyOption\u003dNO_PROXY, proxyServerType\u003dHTTP, password\u003d, proxyServerAddress\u003d, proxyServerPort\u003d0}","platform":"Windows 10"},"type":"TEST_SUITE","name":"Edit_Product_Suite","id":"Test Suites/Edit_Product_Suite","source":"","message":"Test Cases/Edit_Product/component_section","description":"","startTime":1556620106515,"endTime":1556620190085,"childRecords":[{"isOptional":false,"type":"TEST_CASE","name":"Test Cases/Edit_Product/Edit_product_fields","id":"Test Cases/Edit_Product/Edit_product_fields","source":"C:\\\\New-Bugzilla-Application\\\\New_Bugzilla-UI-V2\\\\Test Cases\\\\Edit_Product\\\\Edit_product_fields.tc","message":"Test Cases/Edit_Product/Edit_product_fields","description":"","startTime":1556620107208,"endTime":1556620151986,"childRecords":[{"testStatus":{"stackTrace":"","statusValue":"INFO"},"type":"MESSAGE","name":"","message":"Evaluating variables for test case","startTime":1556620107295,"endTime":0,"childRecords":[],"interuppted":false},{"index":1,"isIgnoredIfFailed":false,"type":"TEST_STEP","name":"openBrowser","message":"Browser is opened with url: \u0027\u0027","description":"","startTime":1556620107735,"endTime":1556620111151,"childRecords":[{"testStatus":{"stackTrace":"","statusValue":"PASSED"},"type":"MESSAGE","name":"","message":"Browser is opened with url: \u0027\u0027","startTime":1556620111150,"endTime":0,"childRecords":[],"interuppted":false}],"interuppted":false},{"index":2,"isIgnoredIfFailed":false,"type":"TEST_STEP","name":"navigateToUrl","message":"Navigate to \u0027https://le-bugsui.staging.corp.arista.io/dashboard\u0027 successfully","description":"","startTime":1556620111152,"endTime":1556620127120,"childRecords":[{"testStatus":{"stackTrace":"","statusValue":"PASSED"},"type":"MESSAGE","name":"","message":"Navigate to \u0027https://le-bugsui.staging.corp.arista.io/dashboard\u0027 successfully","startTime":1556620127119,"endTime":0,"childRecords":[],"interuppted":false}],"interuppted":false},{"index":3,"isIgnoredIfFailed":false,"type":"TEST_STEP","name":"delay","message":"Delayed 3 second(s)","description":"","startTime":1556620127122,"endTime":1556620130161,"childRecords":[{"testStatus":{"stackTrace":"","statusValue":"PASSED"},"type":"MESSAGE","name":"","message":"Delayed 3 second(s)","startTime":1556620130160,"endTime":0,"childRecords":[],"interuppted":false}],"interuppted":false},{"index":4,"isIgnoredIfFailed":false,"type":"TEST_STEP","name":"reusable.loginBugZillaUI.login","message":"reusable.loginBugZillaUI.login is PASSED","description":"","startTime":1556620130162,"endTime":1556620131253,"childRecords":[{"testStatus":{"stackTrace":"","statusValue":"PASSED"},"type":"MESSAGE","name":"","message":"Current window maximized","startTime":1556620130330,"endTime":0,"childRecords":[],"interuppted":false},{"testStatus":{"stackTrace":"","statusValue":"PASSED"},"type":"MESSAGE","name":"","message":"Text \u0027knagendra-ext\u0027 is set on object \u0027Object Repository/Page_BugsUI/input_username\u0027","startTime":1556620130680,"endTime":0,"childRecords":[],"interuppted":false},{"testStatus":{"stackTrace":"","statusValue":"PASSED"},"type":"MESSAGE","name":"","message":"Text \u0027Kum1!@#$%^\u0026*()ar\u0027 is set on object \u0027Object Repository/Page_BugsUI/input_password\u0027","startTime":1556620131061,"endTime":0,"childRecords":[],"interuppted":false},{"testStatus":{"stackTrace":"","statusValue":"PASSED"},"type":"MESSAGE","name":"","message":"Object \u0027Object Repository/Page_BugsUI/button_Login\u0027 is clickable","startTime":1556620131135,"endTime":0,"childRecords":[],"interuppted":false},{"testStatus":{"stackTrace":"","statusValue":"PASSED"},"type":"MESSAGE","name":"","message":"Object: \u0027Object Repository/Page_BugsUI/button_Login\u0027 is clicked on","startTime":1556620131252,"endTime":0,"childRecords":[],"interuppted":false},{"testStatus":{"stackTrace":"","statusValue":"PASSED"},"type":"MESSAGE","name":"","message":"reusable.loginBugZillaUI.login is PASSED","startTime":1556620131253,"endTime":0,"childRecords":[],"interuppted":false}],"interuppted":false},{"index":5,"isIgnoredIfFailed":false,"type":"TEST_STEP","name":"delay","message":"Delayed 6 second(s)","description":"","startTime":1556620131254,"endTime":1556620137256,"childRecords":[{"testStatus":{"stackTrace":"","statusValue":"PASSED"},"type":"MESSAGE","name":"","message":"Delayed 6 second(s)","startTime":1556620137255,"endTime":0,"childRecords":[],"interuppted":false}],"interuppted":false},{"index":6,"isIgnoredIfFailed":false,"type":"TEST_STEP","name":"Statement - If (com.kms.katalon.core.webui.keyword.WebUiBuiltInKeywords.verifyElementPresent(com.kms.katalon.core.testobject.ObjectRepository.findTestObject(Page_BugsUI Dashboard/span_Dashboard), 0))","message":"Object: \u0027Object Repository/Page_BugsUI Dashboard/a_Edit\u0027 is clicked on","description":"","startTime":1556620137256,"endTime":1556620139701,"childRecords":[{"testStatus":{"stackTrace":"","statusValue":"WARNING"},"type":"MESSAGE","name":"","message":"Timeout \u00270\u0027 is invalid. Using default page load timeout: \u002730\u0027","startTime":1556620137292,"endTime":0,"childRecords":[],"interuppted":false},{"testStatus":{"stackTrace":"","statusValue":"PASSED"},"type":"MESSAGE","name":"","message":"Object \u0027Object Repository/Page_BugsUI Dashboard/span_Dashboard\u0027 is present","startTime":1556620137324,"endTime":0,"childRecords":[],"interuppted":false},{"index":1,"isIgnoredIfFailed":false,"type":"TEST_STEP","name":"Statement - If (com.kms.katalon.core.webui.keyword.WebUiBuiltInKeywords.verifyElementPresent(com.kms.katalon.core.testobject.ObjectRepository.findTestObject(Page_BugsUI Dashboard/button_Product), 10))","message":"Object: \u0027Object Repository/Page_BugsUI Dashboard/a_Edit\u0027 is clicked on","description":"","startTime":1556620137325,"endTime":1556620139701,"childRecords":[{"testStatus":{"stackTrace":"","statusValue":"PASSED"},"type":"MESSAGE","name":"","message":"Object \u0027Object Repository/Page_BugsUI Dashboard/button_Product\u0027 is present","startTime":1556620137366,"endTime":0,"childRecords":[],"interuppted":false},{"index":1,"isIgnoredIfFailed":false,"type":"TEST_STEP","name":"click","message":"Object: \u0027Object Repository/Page_BugsUI Dashboard/button_Product\u0027 is clicked on","description":"","startTime":1556620137366,"endTime":1556620137537,"childRecords":[{"testStatus":{"stackTrace":"","statusValue":"PASSED"},"type":"MESSAGE","name":"","message":"Object: \u0027Object Repository/Page_BugsUI Dashboard/button_Product\u0027 is clicked on","startTime":1556620137536,"endTime":0,"childRecords":[],"interuppted":false}],"interuppted":false},{"index":2,"isIgnoredIfFailed":false,"type":"TEST_STEP","name":"delay","message":"Delayed 2 second(s)","description":"","startTime":1556620137539,"endTime":1556620139540,"childRecords":[{"testStatus":{"stackTrace":"","statusValue":"PASSED"},"type":"MESSAGE","name":"","message":"Delayed 2 second(s)","startTime":1556620139540,"endTime":0,"childRecords":[],"interuppted":false}],"interuppted":false},{"index":3,"isIgnoredIfFailed":false,"type":"TEST_STEP","name":"Statement - If (com.kms.katalon.core.webui.keyword.WebUiBuiltInKeywords.verifyElementPresent(com.kms.katalon.core.testobject.ObjectRepository.findTestObject(Page_BugsUI Dashboard/a_Edit), 5))","message":"Object: \u0027Object Repository/Page_BugsUI Dashboard/a_Edit\u0027 is clicked on","description":"","startTime":1556620139541,"endTime":1556620139700,"childRecords":[{"testStatus":{"stackTrace":"","statusValue":"PASSED"},"type":"MESSAGE","name":"","message":"Object \u0027Object Repository/Page_BugsUI Dashboard/a_Edit\u0027 is present","startTime":1556620139567,"endTime":0,"childRecords":[],"interuppted":false},{"index":1,"isIgnoredIfFailed":false,"type":"TEST_STEP","name":"click","message":"Object: \u0027Object Repository/Page_BugsUI Dashboard/a_Edit\u0027 is clicked on","description":"","startTime":1556620139567,"endTime":1556620139700,"childRecords":[{"testStatus":{"stackTrace":"","statusValue":"PASSED"},"type":"MESSAGE","name":"","message":"Object: \u0027Object Repository/Page_BugsUI Dashboard/a_Edit\u0027 is clicked on","startTime":1556620139699,"endTime":0,"childRecords":[],"interuppted":false}],"interuppted":false}],"interuppted":false}],"interuppted":false}],"interuppted":false},{"index":7,"isIgnoredIfFailed":false,"type":"TEST_STEP","name":"verifyElementPresent","message":"Object \u0027Object Repository/Page_BugsUI Edit Product/span_Edit Product\u0027 is present","description":"","startTime":1556620139701,"endTime":1556620142317,"childRecords":[{"testStatus":{"stackTrace":"","statusValue":"WARNING"},"type":"MESSAGE","name":"","message":"Timeout \u00270\u0027 is invalid. Using default page load timeout: \u002730\u0027","startTime":1556620139708,"endTime":0,"childRecords":[],"interuppted":false},{"testStatus":{"stackTrace":"","statusValue":"PASSED"},"type":"MESSAGE","name":"","message":"Object \u0027Object Repository/Page_BugsUI Edit Product/span_Edit Product\u0027 is present","startTime":1556620142316,"endTime":0,"childRecords":[],"interuppted":false}],"interuppted":false},{"index":8,"isIgnoredIfFailed":false,"type":"TEST_STEP","name":"reusable.editPage.selectProduct","message":"reusable.editPage.selectProduct is PASSED","description":"","startTime":1556620142317,"endTime":1556620149411,"childRecords":[{"testStatus":{"stackTrace":"","statusValue":"PASSED"},"type":"MESSAGE","name":"","message":"Text \u0027Software\u0027 is set on object \u0027Object Repository/Page_BugsUI Edit Product/div_Choose Classification\u0027","startTime":1556620142798,"endTime":0,"childRecords":[],"interuppted":false},{"testStatus":{"stackTrace":"","statusValue":"PASSED"},"type":"MESSAGE","name":"","message":"Delayed 2 second(s)","startTime":1556620144799,"endTime":0,"childRecords":[],"interuppted":false},{"testStatus":{"stackTrace":"","statusValue":"PASSED"},"type":"MESSAGE","name":"","message":"Object: \u0027Object Repository/Page_BugsUI Edit Product/span_Software\u0027 is clicked on","startTime":1556620144899,"endTime":0,"childRecords":[],"interuppted":false},{"testStatus":{"stackTrace":"","statusValue":"PASSED"},"type":"MESSAGE","name":"","message":"Text \u00271-Auto-edit\u0027 is set on object \u0027Object Repository/Page_BugsUI Edit Product/div_Choose Product\u0027","startTime":1556620145267,"endTime":0,"childRecords":[],"interuppted":false},{"testStatus":{"stackTrace":"","statusValue":"PASSED"},"type":"MESSAGE","name":"","message":"Delayed 2 second(s)","startTime":1556620147269,"endTime":0,"childRecords":[],"interuppted":false},{"testStatus":{"stackTrace":"","statusValue":"PASSED"},"type":"MESSAGE","name":"","message":"Object: \u0027Object Repository/Page_BugsUI Edit Product/span_1-Auto-edit\u0027 is clicked on","startTime":1556620147408,"endTime":0,"childRecords":[],"interuppted":false},{"testStatus":{"stackTrace":"","statusValue":"PASSED"},"type":"MESSAGE","name":"","message":"Delayed 2 second(s)","startTime":1556620149409,"endTime":0,"childRecords":[],"interuppted":false},{"testStatus":{"stackTrace":"","statusValue":"PASSED"},"type":"MESSAGE","name":"","message":"reusable.editPage.selectProduct is PASSED","startTime":1556620149410,"endTime":0,"childRecords":[],"interuppted":false}],"interuppted":false},{"index":9,"isIgnoredIfFailed":false,"type":"TEST_STEP","name":"verifyElementPresent","message":"Object \u0027Object Repository/Page_BugsUI Edit Product/input_newName\u0027 is present","description":"","startTime":1556620149411,"endTime":1556620149446,"childRecords":[{"testStatus":{"stackTrace":"","statusValue":"WARNING"},"type":"MESSAGE","name":"","message":"Timeout \u00270\u0027 is invalid. Using default page load timeout: \u002730\u0027","startTime":1556620149418,"endTime":0,"childRecords":[],"interuppted":false},{"testStatus":{"stackTrace":"","statusValue":"PASSED"},"type":"MESSAGE","name":"","message":"Object \u0027Object Repository/Page_BugsUI Edit Product/input_newName\u0027 is present","startTime":1556620149445,"endTime":0,"childRecords":[],"interuppted":false}],"interuppted":false},{"index":10,"isIgnoredIfFailed":false,"type":"TEST_STEP","name":"verifyElementPresent","message":"Object \u0027Object Repository/Page_BugsUI Edit Product/textarea_description\u0027 is present","description":"","startTime":1556620149447,"endTime":1556620149474,"childRecords":[{"testStatus":{"stackTrace":"","statusValue":"WARNING"},"type":"MESSAGE","name":"","message":"Timeout \u00270\u0027 is invalid. Using default page load timeout: \u002730\u0027","startTime":1556620149452,"endTime":0,"childRecords":[],"interuppted":false},{"testStatus":{"stackTrace":"","statusValue":"PASSED"},"type":"MESSAGE","name":"","message":"Object \u0027Object Repository/Page_BugsUI Edit Product/textarea_description\u0027 is present","startTime":1556620149473,"endTime":0,"childRecords":[],"interuppted":false}],"interuppted":false},{"index":11,"isIgnoredIfFailed":false,"type":"TEST_STEP","name":"verifyElementPresent","message":"Object \u0027Object Repository/Page_BugsUI Edit Product/div_closed_for_bug_entry\u0027 is present","description":"","startTime":1556620149474,"endTime":1556620149505,"childRecords":[{"testStatus":{"stackTrace":"","statusValue":"WARNING"},"type":"MESSAGE","name":"","message":"Timeout \u00270\u0027 is invalid. Using default page load timeout: \u002730\u0027","startTime":1556620149481,"endTime":0,"childRecords":[],"interuppted":false},{"testStatus":{"stackTrace":"","statusValue":"PASSED"},"type":"MESSAGE","name":"","message":"Object \u0027Object Repository/Page_BugsUI Edit Product/div_closed_for_bug_entry\u0027 is present","startTime":1556620149504,"endTime":0,"childRecords":[],"interuppted":false}],"interuppted":false},{"index":12,"isIgnoredIfFailed":false,"type":"TEST_STEP","name":"Statement - If (com.kms.katalon.core.webui.keyword.WebUiBuiltInKeywords.verifyElementNotClickable(com.kms.katalon.core.testobject.ObjectRepository.findTestObject(Page_BugsUI Edit Product/button_update_product)))","description":"","startTime":1556620149505,"endTime":1556620149602,"childRecords":[{"testStatus":{"stackTrace":"","statusValue":"PASSED"},"type":"MESSAGE","name":"","message":"Object \u0027Object Repository/Page_BugsUI Edit Product/button_update_product\u0027 is NOT clickable","startTime":1556620149600,"endTime":0,"childRecords":[],"interuppted":false},{"index":1,"isIgnoredIfFailed":false,"type":"TEST_STEP","name":"Statement - assert true","description":"","startTime":1556620149601,"endTime":1556620149602,"childRecords":[],"interuppted":false}],"interuppted":false},{"index":14,"isIgnoredIfFailed":false,"type":"TEST_STEP","name":"scrollToElement","message":"Scroll to object \u0027Object Repository/Page_BugsUI Edit Product/button_Delete Product\u0027 successfully","description":"","startTime":1556620149603,"endTime":1556620149731,"childRecords":[{"testStatus":{"stackTrace":"","statusValue":"PASSED"},"type":"MESSAGE","name":"","message":"Scroll to object \u0027Object Repository/Page_BugsUI Edit Product/button_Delete Product\u0027 successfully","startTime":1556620149731,"endTime":0,"childRecords":[],"interuppted":false}],"interuppted":false},{"index":15,"isIgnoredIfFailed":false,"type":"TEST_STEP","name":"verifyElementPresent","message":"Object \u0027Object Repository/Page_BugsUI Edit Product/div_Component Information\u0027 is present","description":"","startTime":1556620149732,"endTime":1556620149771,"childRecords":[{"testStatus":{"stackTrace":"","statusValue":"WARNING"},"type":"MESSAGE","name":"","message":"Timeout \u00270\u0027 is invalid. Using default page load timeout: \u002730\u0027","startTime":1556620149738,"endTime":0,"childRecords":[],"interuppted":false},{"testStatus":{"stackTrace":"","statusValue":"PASSED"},"type":"MESSAGE","name":"","message":"Object \u0027Object Repository/Page_BugsUI Edit Product/div_Component Information\u0027 is present","startTime":1556620149771,"endTime":0,"childRecords":[],"interuppted":false}],"interuppted":false},{"index":16,"isIgnoredIfFailed":false,"type":"TEST_STEP","name":"verifyElementPresent","message":"Object \u0027Object Repository/Page_BugsUI Edit Product/button_Refresh components\u0027 is present","description":"","startTime":1556620149772,"endTime":1556620149803,"childRecords":[{"testStatus":{"stackTrace":"","statusValue":"WARNING"},"type":"MESSAGE","name":"","message":"Timeout \u00270\u0027 is invalid. Using default page load timeout: \u002730\u0027","startTime":1556620149777,"endTime":0,"childRecords":[],"interuppted":false},{"testStatus":{"stackTrace":"","statusValue":"PASSED"},"type":"MESSAGE","name":"","message":"Object \u0027Object Repository/Page_BugsUI Edit Product/button_Refresh components\u0027 is present","startTime":1556620149803,"endTime":0,"childRecords":[],"interuppted":false}],"interuppted":false},{"index":17,"isIgnoredIfFailed":false,"type":"TEST_STEP","name":"verifyElementPresent","message":"Object \u0027Object Repository/Page_BugsUI Edit Product/button_AddNewRow_Component\u0027 is present","description":"","startTime":1556620149803,"endTime":1556620149848,"childRecords":[{"testStatus":{"stackTrace":"","statusValue":"WARNING"},"type":"MESSAGE","name":"","message":"Timeout \u00270\u0027 is invalid. Using default page load timeout: \u002730\u0027","startTime":1556620149808,"endTime":0,"childRecords":[],"interuppted":false},{"testStatus":{"stackTrace":"","statusValue":"PASSED"},"type":"MESSAGE","name":"","message":"Object \u0027Object Repository/Page_BugsUI Edit Product/button_AddNewRow_Component\u0027 is present","startTime":1556620149846,"endTime":0,"childRecords":[],"interuppted":false}],"interuppted":false},{"index":18,"isIgnoredIfFailed":false,"type":"TEST_STEP","name":"verifyElementPresent","message":"Object \u0027Object Repository/Page_BugsUI Edit Product/span_Version Information\u0027 is present","description":"","startTime":1556620149849,"endTime":1556620149894,"childRecords":[{"testStatus":{"stackTrace":"","statusValue":"WARNING"},"type":"MESSAGE","name":"","message":"Timeout \u00270\u0027 is invalid. Using default page load timeout: \u002730\u0027","startTime":1556620149854,"endTime":0,"childRecords":[],"interuppted":false},{"testStatus":{"stackTrace":"","statusValue":"PASSED"},"type":"MESSAGE","name":"","message":"Object \u0027Object Repository/Page_BugsUI Edit Product/span_Version Information\u0027 is present","startTime":1556620149894,"endTime":0,"childRecords":[],"interuppted":false}],"interuppted":false},{"index":19,"isIgnoredIfFailed":false,"type":"TEST_STEP","name":"verifyElementPresent","message":"Object \u0027Object Repository/Page_BugsUI Edit Product/button_Refresh versions\u0027 is present","description":"","startTime":1556620149894,"endTime":1556620149945,"childRecords":[{"testStatus":{"stackTrace":"","statusValue":"WARNING"},"type":"MESSAGE","name":"","message":"Timeout \u00270\u0027 is invalid. Using default page load timeout: \u002730\u0027","startTime":1556620149900,"endTime":0,"childRecords":[],"interuppted":false},{"testStatus":{"stackTrace":"","statusValue":"PASSED"},"type":"MESSAGE","name":"","message":"Object \u0027Object Repository/Page_BugsUI Edit Product/button_Refresh versions\u0027 is present","startTime":1556620149945,"endTime":0,"childRecords":[],"interuppted":false}],"interuppted":false},{"index":20,"isIgnoredIfFailed":false,"type":"TEST_STEP","name":"verifyElementPresent","message":"Object \u0027Object Repository/Page_BugsUI Edit Product/button_AddNewRow_version\u0027 is present","description":"","startTime":1556620149946,"endTime":1556620149982,"childRecords":[{"testStatus":{"stackTrace":"","statusValue":"WARNING"},"type":"MESSAGE","name":"","message":"Timeout \u00270\u0027 is invalid. Using default page load timeout: \u002730\u0027","startTime":1556620149952,"endTime":0,"childRecords":[],"interuppted":false},{"testStatus":{"stackTrace":"","statusValue":"PASSED"},"type":"MESSAGE","name":"","message":"Object \u0027Object Repository/Page_BugsUI Edit Product/button_AddNewRow_version\u0027 is present","startTime":1556620149982,"endTime":0,"childRecords":[],"interuppted":false}],"interuppted":false},{"index":21,"isIgnoredIfFailed":false,"type":"TEST_STEP","name":"delay","message":"Delayed 2 second(s)","description":"","startTime":1556620149982,"endTime":1556620151984,"childRecords":[{"testStatus":{"stackTrace":"","statusValue":"PASSED"},"type":"MESSAGE","name":"","message":"Delayed 2 second(s)","startTime":1556620151984,"endTime":0,"childRecords":[],"interuppted":false}],"interuppted":false},{"testStatus":{"stackTrace":"","statusValue":"PASSED"},"type":"MESSAGE","name":"","message":"Test Cases/Edit_Product/Edit_product_fields","startTime":1556620151984,"endTime":0,"childRecords":[],"interuppted":false}],"interuppted":false},{"isOptional":false,"type":"TEST_CASE","name":"Test Cases/Edit_Product/verify_values_prepopulated","id":"Test Cases/Edit_Product/verify_values_prepopulated","source":"C:\\\\New-Bugzilla-Application\\\\New_Bugzilla-UI-V2\\\\Test Cases\\\\Edit_Product\\\\verify_values_prepopulated.tc","message":"Test Cases/Edit_Product/verify_values_prepopulated","description":"","startTime":1556620152002,"endTime":1556620154970,"childRecords":[{"testStatus":{"stackTrace":"","statusValue":"INFO"},"type":"MESSAGE","name":"","message":"Evaluating variables for test case","startTime":1556620152044,"endTime":0,"childRecords":[],"interuppted":false},{"index":1,"isIgnoredIfFailed":false,"type":"TEST_STEP","name":"scrollToElement","message":"Scroll to object \u0027Object Repository/Page_BugsUI Edit Product/input_newName\u0027 successfully","description":"","startTime":1556620152451,"endTime":1556620152540,"childRecords":[{"testStatus":{"stackTrace":"","statusValue":"PASSED"},"type":"MESSAGE","name":"","message":"Scroll to object \u0027Object Repository/Page_BugsUI Edit Product/input_newName\u0027 successfully","startTime":1556620152539,"endTime":0,"childRecords":[],"interuppted":false}],"interuppted":false},{"index":2,"isIgnoredIfFailed":false,"type":"TEST_STEP","name":"Statement - productName \u003d com.kms.katalon.core.webui.keyword.WebUiBuiltInKeywords.getAttribute(com.kms.katalon.core.testobject.ObjectRepository.findTestObject(Page_BugsUI Edit Product/input_newName), \"value\")","message":"Attribute \u0027value\u0027 of object \u0027Object Repository/Page_BugsUI Edit Product/input_newName\u0027 is: \u00271-Auto-edit\u0027","description":"","startTime":1556620152540,"endTime":1556620152645,"childRecords":[{"testStatus":{"stackTrace":"","statusValue":"PASSED"},"type":"MESSAGE","name":"","message":"Attribute \u0027value\u0027 of object \u0027Object Repository/Page_BugsUI Edit Product/input_newName\u0027 is: \u00271-Auto-edit\u0027","startTime":1556620152644,"endTime":0,"childRecords":[],"interuppted":false}],"interuppted":false},{"index":3,"isIgnoredIfFailed":false,"type":"TEST_STEP","name":"Statement - productDescription \u003d com.kms.katalon.core.webui.keyword.WebUiBuiltInKeywords.getAttribute(com.kms.katalon.core.testobject.ObjectRepository.findTestObject(Page_BugsUI Edit Product/textarea_description), \"value\")","message":"Attribute \u0027value\u0027 of object \u0027Object Repository/Page_BugsUI Edit Product/textarea_description\u0027 is: \u0027This product created for Automation of Edit page functionalities.\u0027","description":"","startTime":1556620152645,"endTime":1556620152692,"childRecords":[{"testStatus":{"stackTrace":"","statusValue":"PASSED"},"type":"MESSAGE","name":"","message":"Attribute \u0027value\u0027 of object \u0027Object Repository/Page_BugsUI Edit Product/textarea_description\u0027 is: \u0027This product created for Automation of Edit page functionalities.\u0027","startTime":1556620152692,"endTime":0,"childRecords":[],"interuppted":false}],"interuppted":false},{"index":4,"isIgnoredIfFailed":false,"type":"TEST_STEP","name":"Statement - If (productName.equals(\"1-Auto-edit\"))","description":"","startTime":1556620152692,"endTime":1556620152695,"childRecords":[{"index":1,"isIgnoredIfFailed":false,"type":"TEST_STEP","name":"Statement - assert true","description":"","startTime":1556620152695,"endTime":1556620152695,"childRecords":[],"interuppted":false}],"interuppted":false},{"index":6,"isIgnoredIfFailed":false,"type":"TEST_STEP","name":"Statement - If (!(productDescription.isEmpty()))","description":"","startTime":1556620152696,"endTime":1556620152698,"childRecords":[{"index":1,"isIgnoredIfFailed":false,"type":"TEST_STEP","name":"Statement - assert true","description":"","startTime":1556620152697,"endTime":1556620152697,"childRecords":[],"interuppted":false}],"interuppted":false},{"index":8,"isIgnoredIfFailed":false,"type":"TEST_STEP","name":"verifyElementNotClickable","message":"Object \u0027Object Repository/Page_BugsUI Edit Product/unknown_Component\u0027 is NOT clickable","description":"","startTime":1556620152698,"endTime":1556620152758,"childRecords":[{"testStatus":{"stackTrace":"","statusValue":"PASSED"},"type":"MESSAGE","name":"","message":"Object \u0027Object Repository/Page_BugsUI Edit Product/unknown_Component\u0027 is NOT clickable","startTime":1556620152758,"endTime":0,"childRecords":[],"interuppted":false}],"interuppted":false},{"index":9,"isIgnoredIfFailed":false,"type":"TEST_STEP","name":"Statement - unkownComponentName \u003d com.kms.katalon.core.webui.keyword.WebUiBuiltInKeywords.getAttribute(com.kms.katalon.core.testobject.ObjectRepository.findTestObject(Page_BugsUI Edit Product/unknown_Component), \"value\")","message":"Attribute \u0027value\u0027 of object \u0027Object Repository/Page_BugsUI Edit Product/unknown_Component\u0027 is: \u0027Unknown\u0027","description":"","startTime":1556620152759,"endTime":1556620152800,"childRecords":[{"testStatus":{"stackTrace":"","statusValue":"PASSED"},"type":"MESSAGE","name":"","message":"Attribute \u0027value\u0027 of object \u0027Object Repository/Page_BugsUI Edit Product/unknown_Component\u0027 is: \u0027Unknown\u0027","startTime":1556620152799,"endTime":0,"childRecords":[],"interuppted":false}],"interuppted":false},{"index":10,"isIgnoredIfFailed":false,"type":"TEST_STEP","name":"Statement - If (unkownComponentName.equals(\"Unknown\"))","description":"","startTime":1556620152800,"endTime":1556620152801,"childRecords":[{"index":1,"isIgnoredIfFailed":false,"type":"TEST_STEP","name":"Statement - assert true","description":"","startTime":1556620152800,"endTime":1556620152801,"childRecords":[],"interuppted":false}],"interuppted":false},{"index":12,"isIgnoredIfFailed":false,"type":"TEST_STEP","name":"Statement - unkownComponentDesc \u003d com.kms.katalon.core.webui.keyword.WebUiBuiltInKeywords.getAttribute(com.kms.katalon.core.testobject.ObjectRepository.findTestObject(Page_BugsUI Edit Product/unkown_description), \"value\")","message":"Attribute \u0027value\u0027 of object \u0027Object Repository/Page_BugsUI Edit Product/unkown_description\u0027 is: \u0027unknown\u0027","description":"","startTime":1556620152801,"endTime":1556620152865,"childRecords":[{"testStatus":{"stackTrace":"","statusValue":"PASSED"},"type":"MESSAGE","name":"","message":"Attribute \u0027value\u0027 of object \u0027Object Repository/Page_BugsUI Edit Product/unkown_description\u0027 is: \u0027unknown\u0027","startTime":1556620152865,"endTime":0,"childRecords":[],"interuppted":false}],"interuppted":false},{"index":13,"isIgnoredIfFailed":false,"type":"TEST_STEP","name":"Statement - unkownComponentDefaultAsignee \u003d com.kms.katalon.core.webui.keyword.WebUiBuiltInKeywords.getAttribute(com.kms.katalon.core.testobject.ObjectRepository.findTestObject(Page_BugsUI Edit Product/unkown_defaultAssignee), \"value\")","message":"Attribute \u0027value\u0027 of object \u0027Object Repository/Page_BugsUI Edit Product/unkown_defaultAssignee\u0027 is: \u0027kumar.nagendra@happiestminds.com\u0027","description":"","startTime":1556620152865,"endTime":1556620152966,"childRecords":[{"testStatus":{"stackTrace":"","statusValue":"PASSED"},"type":"MESSAGE","name":"","message":"Attribute \u0027value\u0027 of object \u0027Object Repository/Page_BugsUI Edit Product/unkown_defaultAssignee\u0027 is: \u0027kumar.nagendra@happiestminds.com\u0027","startTime":1556620152965,"endTime":0,"childRecords":[],"interuppted":false}],"interuppted":false},{"index":14,"isIgnoredIfFailed":false,"type":"TEST_STEP","name":"Statement - If (!(unkownComponentDesc.isEmpty()) \u0026\u0026 !(unkownComponentDefaultAsignee.isEmpty()))","description":"","startTime":1556620152966,"endTime":1556620152968,"childRecords":[{"index":1,"isIgnoredIfFailed":false,"type":"TEST_STEP","name":"Statement - assert true","description":"","startTime":1556620152967,"endTime":1556620152967,"childRecords":[],"interuppted":false}],"interuppted":false},{"index":16,"isIgnoredIfFailed":false,"type":"TEST_STEP","name":"delay","message":"Delayed 2 second(s)","description":"","startTime":1556620152968,"endTime":1556620154969,"childRecords":[{"testStatus":{"stackTrace":"","statusValue":"PASSED"},"type":"MESSAGE","name":"","message":"Delayed 2 second(s)","startTime":1556620154969,"endTime":0,"childRecords":[],"interuppted":false}],"interuppted":false},{"testStatus":{"stackTrace":"","statusValue":"PASSED"},"type":"MESSAGE","name":"","message":"Test Cases/Edit_Product/verify_values_prepopulated","startTime":1556620154969,"endTime":0,"childRecords":[],"interuppted":false}],"interuppted":false},{"isOptional":false,"type":"TEST_CASE","name":"Test Cases/Edit_Product/default_UnknownComponent","id":"Test Cases/Edit_Product/default_UnknownComponent","source":"C:\\\\New-Bugzilla-Application\\\\New_Bugzilla-UI-V2\\\\Test Cases\\\\Edit_Product\\\\default_UnknownComponent.tc","message":"Test Cases/Edit_Product/default_UnknownComponent","description":"","startTime":1556620154972,"endTime":1556620174712,"childRecords":[{"testStatus":{"stackTrace":"","statusValue":"INFO"},"type":"MESSAGE","name":"","message":"Evaluating variables for test case","startTime":1556620155008,"endTime":0,"childRecords":[],"interuppted":false},{"index":1,"isIgnoredIfFailed":false,"type":"TEST_STEP","name":"Statement - If (com.kms.katalon.core.webui.keyword.WebUiBuiltInKeywords.verifyElementPresent(com.kms.katalon.core.testobject.ObjectRepository.findTestObject(Page_BugsUI Edit Product/delete_icon_unknownCompnent), 0))","message":"Object: \u0027Object Repository/Page_BugsUI Edit Product/delete_icon_unknownCompnent\u0027 is clicked on","description":"","startTime":1556620155221,"endTime":1556620155364,"childRecords":[{"testStatus":{"stackTrace":"","statusValue":"WARNING"},"type":"MESSAGE","name":"","message":"Timeout \u00270\u0027 is invalid. Using default page load timeout: \u002730\u0027","startTime":1556620155226,"endTime":0,"childRecords":[],"interuppted":false},{"testStatus":{"stackTrace":"","statusValue":"PASSED"},"type":"MESSAGE","name":"","message":"Object \u0027Object Repository/Page_BugsUI Edit Product/delete_icon_unknownCompnent\u0027 is present","startTime":1556620155249,"endTime":0,"childRecords":[],"interuppted":false},{"index":1,"isIgnoredIfFailed":false,"type":"TEST_STEP","name":"click","message":"Object: \u0027Object Repository/Page_BugsUI Edit Product/delete_icon_unknownCompnent\u0027 is clicked on","description":"","startTime":1556620155250,"endTime":1556620155364,"childRecords":[{"testStatus":{"stackTrace":"","statusValue":"PASSED"},"type":"MESSAGE","name":"","message":"Object: \u0027Object Repository/Page_BugsUI Edit Product/delete_icon_unknownCompnent\u0027 is clicked on","startTime":1556620155363,"endTime":0,"childRecords":[],"interuppted":false}],"interuppted":false}],"interuppted":false},{"index":2,"isIgnoredIfFailed":false,"type":"TEST_STEP","name":"delay","message":"Delayed 2 second(s)","description":"","startTime":1556620155365,"endTime":1556620157368,"childRecords":[{"testStatus":{"stackTrace":"","statusValue":"PASSED"},"type":"MESSAGE","name":"","message":"Delayed 2 second(s)","startTime":1556620157368,"endTime":0,"childRecords":[],"interuppted":false}],"interuppted":false},{"index":3,"isIgnoredIfFailed":false,"type":"TEST_STEP","name":"Statement - If (com.kms.katalon.core.webui.keyword.WebUiBuiltInKeywords.verifyElementPresent(com.kms.katalon.core.testobject.ObjectRepository.findTestObject(Page_BugsUI Edit Product/confirmDeleteProduct_popup), 0))","message":"Object: \u0027Object Repository/Page_BugsUI Edit Product/button_component_Yes\u0027 is clicked on","description":"","startTime":1556620157369,"endTime":1556620157572,"childRecords":[{"testStatus":{"stackTrace":"","statusValue":"WARNING"},"type":"MESSAGE","name":"","message":"Timeout \u00270\u0027 is invalid. Using default page load timeout: \u002730\u0027","startTime":1556620157373,"endTime":0,"childRecords":[],"interuppted":false},{"testStatus":{"stackTrace":"","statusValue":"PASSED"},"type":"MESSAGE","name":"","message":"Object \u0027Object Repository/Page_BugsUI Edit Product/confirmDeleteProduct_popup\u0027 is present","startTime":1556620157397,"endTime":0,"childRecords":[],"interuppted":false},{"index":1,"isIgnoredIfFailed":false,"type":"TEST_STEP","name":"Statement - If (com.kms.katalon.core.webui.keyword.WebUiBuiltInKeywords.verifyElementPresent(com.kms.katalon.core.testobject.ObjectRepository.findTestObject(Page_BugsUI Edit Product/button_component_Yes), 0))","message":"Object: \u0027Object Repository/Page_BugsUI Edit Product/button_component_Yes\u0027 is clicked on","description":"","startTime":1556620157397,"endTime":1556620157572,"childRecords":[{"testStatus":{"stackTrace":"","statusValue":"WARNING"},"type":"MESSAGE","name":"","message":"Timeout \u00270\u0027 is invalid. Using default page load timeout: \u002730\u0027","startTime":1556620157403,"endTime":0,"childRecords":[],"interuppted":false},{"testStatus":{"stackTrace":"","statusValue":"PASSED"},"type":"MESSAGE","name":"","message":"Object \u0027Object Repository/Page_BugsUI Edit Product/button_component_Yes\u0027 is present","startTime":1556620157425,"endTime":0,"childRecords":[],"interuppted":false},{"index":1,"isIgnoredIfFailed":false,"type":"TEST_STEP","name":"click","message":"Object: \u0027Object Repository/Page_BugsUI Edit Product/button_component_Yes\u0027 is clicked on","description":"","startTime":1556620157427,"endTime":1556620157572,"childRecords":[{"testStatus":{"stackTrace":"","statusValue":"PASSED"},"type":"MESSAGE","name":"","message":"Object: \u0027Object Repository/Page_BugsUI Edit Product/button_component_Yes\u0027 is clicked on","startTime":1556620157571,"endTime":0,"childRecords":[],"interuppted":false}],"interuppted":false}],"interuppted":false}],"interuppted":false},{"index":4,"isIgnoredIfFailed":false,"type":"TEST_STEP","name":"delay","message":"Delayed 2 second(s)","description":"","startTime":1556620157573,"endTime":1556620159575,"childRecords":[{"testStatus":{"stackTrace":"","statusValue":"PASSED"},"type":"MESSAGE","name":"","message":"Delayed 2 second(s)","startTime":1556620159574,"endTime":0,"childRecords":[],"interuppted":false}],"interuppted":false},{"index":5,"isIgnoredIfFailed":false,"type":"TEST_STEP","name":"Statement - If (com.kms.katalon.core.webui.keyword.WebUiBuiltInKeywords.verifyElementPresent(com.kms.katalon.core.testobject.ObjectRepository.findTestObject(Page_BugsUI Edit Product/div_Product must have at least), 0))","description":"","startTime":1556620159575,"endTime":1556620159717,"childRecords":[{"testStatus":{"stackTrace":"","statusValue":"WARNING"},"type":"MESSAGE","name":"","message":"Timeout \u00270\u0027 is invalid. Using default page load timeout: \u002730\u0027","startTime":1556620159580,"endTime":0,"childRecords":[],"interuppted":false},{"testStatus":{"stackTrace":"","statusValue":"PASSED"},"type":"MESSAGE","name":"","message":"Object \u0027Object Repository/Page_BugsUI Edit Product/div_Product must have at least\u0027 is present","startTime":1556620159619,"endTime":0,"childRecords":[],"interuppted":false},{"index":1,"isIgnoredIfFailed":false,"type":"TEST_STEP","name":"Statement - warningMessage \u003d com.kms.katalon.core.webui.keyword.WebUiBuiltInKeywords.getText(com.kms.katalon.core.testobject.ObjectRepository.findTestObject(Page_BugsUI Edit Product/div_Product must have at least))","message":"Text of object \u0027Object Repository/Page_BugsUI Edit Product/div_Product must have at least\u0027 is: \u0027Product must have at least 1 component.\u0027","description":"","startTime":1556620159619,"endTime":1556620159715,"childRecords":[{"testStatus":{"stackTrace":"","statusValue":"PASSED"},"type":"MESSAGE","name":"","message":"Text of object \u0027Object Repository/Page_BugsUI Edit Product/div_Product must have at least\u0027 is: \u0027Product must have at least 1 component.\u0027","startTime":1556620159714,"endTime":0,"childRecords":[],"interuppted":false}],"interuppted":false},{"index":2,"isIgnoredIfFailed":false,"type":"TEST_STEP","name":"Statement - If (warningMessage.equals(\"Product must have at least 1 component.\"))","description":"","startTime":1556620159715,"endTime":1556620159717,"childRecords":[{"index":1,"isIgnoredIfFailed":false,"type":"TEST_STEP","name":"Statement - assert true","description":"","startTime":1556620159716,"endTime":1556620159716,"childRecords":[],"interuppted":false}],"interuppted":false}],"interuppted":false},{"index":6,"isIgnoredIfFailed":false,"type":"TEST_STEP","name":"delay","message":"Delayed 3 second(s)","description":"","startTime":1556620159717,"endTime":1556620162719,"childRecords":[{"testStatus":{"stackTrace":"","statusValue":"PASSED"},"type":"MESSAGE","name":"","message":"Delayed 3 second(s)","startTime":1556620162718,"endTime":0,"childRecords":[],"interuppted":false}],"interuppted":false},{"index":7,"isIgnoredIfFailed":false,"type":"TEST_STEP","name":"Statement - If (com.kms.katalon.core.webui.keyword.WebUiBuiltInKeywords.verifyElementPresent(com.kms.katalon.core.testobject.ObjectRepository.findTestObject(Page_BugsUI Edit Product/update_icon_unknownComponent), 0))","description":"","startTime":1556620162719,"endTime":1556620162945,"childRecords":[{"testStatus":{"stackTrace":"","statusValue":"WARNING"},"type":"MESSAGE","name":"","message":"Timeout \u00270\u0027 is invalid. Using default page load timeout: \u002730\u0027","startTime":1556620162724,"endTime":0,"childRecords":[],"interuppted":false},{"testStatus":{"stackTrace":"","statusValue":"PASSED"},"type":"MESSAGE","name":"","message":"Object \u0027Object Repository/Page_BugsUI Edit Product/update_icon_unknownComponent\u0027 is present","startTime":1556620162742,"endTime":0,"childRecords":[],"interuppted":false},{"index":1,"isIgnoredIfFailed":false,"type":"TEST_STEP","name":"click","message":"Object: \u0027Object Repository/Page_BugsUI Edit Product/update_icon_unknownComponent\u0027 is clicked on","description":"","startTime":1556620162743,"endTime":1556620162840,"childRecords":[{"testStatus":{"stackTrace":"","statusValue":"PASSED"},"type":"MESSAGE","name":"","message":"Object: \u0027Object Repository/Page_BugsUI Edit Product/update_icon_unknownComponent\u0027 is clicked on","startTime":1556620162839,"endTime":0,"childRecords":[],"interuppted":false}],"interuppted":false},{"index":2,"isIgnoredIfFailed":false,"type":"TEST_STEP","name":"Statement - If (com.kms.katalon.core.webui.keyword.WebUiBuiltInKeywords.verifyElementPresent(com.kms.katalon.core.testobject.ObjectRepository.findTestObject(Page_BugsUI Edit Product/div_Nothing to update), 0))","description":"","startTime":1556620162840,"endTime":1556620162945,"childRecords":[{"testStatus":{"stackTrace":"","statusValue":"WARNING"},"type":"MESSAGE","name":"","message":"Timeout \u00270\u0027 is invalid. Using default page load timeout: \u002730\u0027","startTime":1556620162846,"endTime":0,"childRecords":[],"interuppted":false},{"testStatus":{"stackTrace":"","statusValue":"PASSED"},"type":"MESSAGE","name":"","message":"Object \u0027Object Repository/Page_BugsUI Edit Product/div_Nothing to update\u0027 is present","startTime":1556620162874,"endTime":0,"childRecords":[],"interuppted":false},{"index":1,"isIgnoredIfFailed":false,"type":"TEST_STEP","name":"Statement - nothingToUpdate \u003d com.kms.katalon.core.webui.keyword.WebUiBuiltInKeywords.getText(com.kms.katalon.core.testobject.ObjectRepository.findTestObject(Page_BugsUI Edit Product/div_Nothing to update))","message":"Text of object \u0027Object Repository/Page_BugsUI Edit Product/div_Nothing to update\u0027 is: \u0027Nothing to update.\u0027","description":"","startTime":1556620162875,"endTime":1556620162943,"childRecords":[{"testStatus":{"stackTrace":"","statusValue":"PASSED"},"type":"MESSAGE","name":"","message":"Text of object \u0027Object Repository/Page_BugsUI Edit Product/div_Nothing to update\u0027 is: \u0027Nothing to update.\u0027","startTime":1556620162943,"endTime":0,"childRecords":[],"interuppted":false}],"interuppted":false},{"index":2,"isIgnoredIfFailed":false,"type":"TEST_STEP","name":"Statement - If (nothingToUpdate.equals(\"Nothing to update.\"))","description":"","startTime":1556620162943,"endTime":1556620162944,"childRecords":[{"index":1,"isIgnoredIfFailed":false,"type":"TEST_STEP","name":"Statement - assert true","description":"","startTime":1556620162944,"endTime":1556620162944,"childRecords":[],"interuppted":false}],"interuppted":false}],"interuppted":false}],"interuppted":false},{"index":8,"isIgnoredIfFailed":false,"type":"TEST_STEP","name":"clearText","message":"Text of object \u0027Object Repository/Page_BugsUI Edit Product/unkown_description\u0027 is cleared","description":"","startTime":1556620162945,"endTime":1556620163032,"childRecords":[{"testStatus":{"stackTrace":"","statusValue":"PASSED"},"type":"MESSAGE","name":"","message":"Text of object \u0027Object Repository/Page_BugsUI Edit Product/unkown_description\u0027 is cleared","startTime":1556620163031,"endTime":0,"childRecords":[],"interuppted":false}],"interuppted":false},{"index":9,"isIgnoredIfFailed":false,"type":"TEST_STEP","name":"setText","message":"Text \u0027unknown1234\u0027 is set on object \u0027Object Repository/Page_BugsUI Edit Product/unkown_description\u0027","description":"","startTime":1556620163033,"endTime":1556620163293,"childRecords":[{"testStatus":{"stackTrace":"","statusValue":"PASSED"},"type":"MESSAGE","name":"","message":"Text \u0027unknown1234\u0027 is set on object \u0027Object Repository/Page_BugsUI Edit Product/unkown_description\u0027","startTime":1556620163293,"endTime":0,"childRecords":[],"interuppted":false}],"interuppted":false},{"index":10,"isIgnoredIfFailed":false,"type":"TEST_STEP","name":"clearText","message":"Text of object \u0027Object Repository/Page_BugsUI Edit Product/unkown_defaultAssignee\u0027 is cleared","description":"","startTime":1556620163293,"endTime":1556620163402,"childRecords":[{"testStatus":{"stackTrace":"","statusValue":"PASSED"},"type":"MESSAGE","name":"","message":"Text of object \u0027Object Repository/Page_BugsUI Edit Product/unkown_defaultAssignee\u0027 is cleared","startTime":1556620163402,"endTime":0,"childRecords":[],"interuppted":false}],"interuppted":false},{"index":11,"isIgnoredIfFailed":false,"type":"TEST_STEP","name":"setText","message":"Text \u0027divya.r@happiestminds.com\u0027 is set on object \u0027Object Repository/Page_BugsUI Edit Product/unkown_defaultAssignee\u0027","description":"","startTime":1556620163402,"endTime":1556620163713,"childRecords":[{"testStatus":{"stackTrace":"","statusValue":"PASSED"},"type":"MESSAGE","name":"","message":"Text \u0027divya.r@happiestminds.com\u0027 is set on object \u0027Object Repository/Page_BugsUI Edit Product/unkown_defaultAssignee\u0027","startTime":1556620163713,"endTime":0,"childRecords":[],"interuppted":false}],"interuppted":false},{"index":12,"isIgnoredIfFailed":false,"type":"TEST_STEP","name":"click","message":"Object: \u0027Object Repository/Page_BugsUI Edit Product/update_icon_unknownComponent\u0027 is clicked on","description":"","startTime":1556620163714,"endTime":1556620163807,"childRecords":[{"testStatus":{"stackTrace":"","statusValue":"PASSED"},"type":"MESSAGE","name":"","message":"Object: \u0027Object Repository/Page_BugsUI Edit Product/update_icon_unknownComponent\u0027 is clicked on","startTime":1556620163806,"endTime":0,"childRecords":[],"interuppted":false}],"interuppted":false},{"index":13,"isIgnoredIfFailed":false,"type":"TEST_STEP","name":"Statement - If (com.kms.katalon.core.webui.keyword.WebUiBuiltInKeywords.verifyElementPresent(com.kms.katalon.core.testobject.ObjectRepository.findTestObject(Page_BugsUI Edit Product/div_Component has been updated), 0))","description":"","startTime":1556620163807,"endTime":1556620164910,"childRecords":[{"testStatus":{"stackTrace":"","statusValue":"WARNING"},"type":"MESSAGE","name":"","message":"Timeout \u00270\u0027 is invalid. Using default page load timeout: \u002730\u0027","startTime":1556620163811,"endTime":0,"childRecords":[],"interuppted":false},{"testStatus":{"stackTrace":"","statusValue":"PASSED"},"type":"MESSAGE","name":"","message":"Object \u0027Object Repository/Page_BugsUI Edit Product/div_Component has been updated\u0027 is present","startTime":1556620164867,"endTime":0,"childRecords":[],"interuppted":false},{"index":1,"isIgnoredIfFailed":false,"type":"TEST_STEP","name":"Statement - componentUpdatedMsg \u003d com.kms.katalon.core.webui.keyword.WebUiBuiltInKeywords.getText(com.kms.katalon.core.testobject.ObjectRepository.findTestObject(Page_BugsUI Edit Product/div_Component has been updated))","message":"Text of object \u0027Object Repository/Page_BugsUI Edit Product/div_Component has been updated\u0027 is: \u0027Component has been updated successfully.\u0027","description":"","startTime":1556620164867,"endTime":1556620164909,"childRecords":[{"testStatus":{"stackTrace":"","statusValue":"PASSED"},"type":"MESSAGE","name":"","message":"Text of object \u0027Object Repository/Page_BugsUI Edit Product/div_Component has been updated\u0027 is: \u0027Component has been updated successfully.\u0027","startTime":1556620164909,"endTime":0,"childRecords":[],"interuppted":false}],"interuppted":false},{"index":2,"isIgnoredIfFailed":false,"type":"TEST_STEP","name":"Statement - If (componentUpdatedMsg.equals(\"Component has been updated successfully.\"))","description":"","startTime":1556620164910,"endTime":1556620164910,"childRecords":[{"index":1,"isIgnoredIfFailed":false,"type":"TEST_STEP","name":"Statement - assert true","description":"","startTime":1556620164910,"endTime":1556620164910,"childRecords":[],"interuppted":false}],"interuppted":false}],"interuppted":false},{"index":14,"isIgnoredIfFailed":false,"type":"TEST_STEP","name":"delay","message":"Delayed 4 second(s)","description":"","startTime":1556620164911,"endTime":1556620168912,"childRecords":[{"testStatus":{"stackTrace":"","statusValue":"PASSED"},"type":"MESSAGE","name":"","message":"Delayed 4 second(s)","startTime":1556620168912,"endTime":0,"childRecords":[],"interuppted":false}],"interuppted":false},{"index":15,"isIgnoredIfFailed":false,"type":"TEST_STEP","name":"reusable.editPage.resetUnkownComponent","message":"reusable.editPage.resetUnkownComponent is PASSED","description":"","startTime":1556620168912,"endTime":1556620171709,"childRecords":[{"testStatus":{"stackTrace":"","statusValue":"PASSED"},"type":"MESSAGE","name":"","message":"Text of object \u0027Object Repository/Page_BugsUI Edit Product/unkown_description\u0027 is cleared","startTime":1556620168962,"endTime":0,"childRecords":[],"interuppted":false},{"testStatus":{"stackTrace":"","statusValue":"PASSED"},"type":"MESSAGE","name":"","message":"Text \u0027unknown\u0027 is set on object \u0027Object Repository/Page_BugsUI Edit Product/unkown_description\u0027","startTime":1556620169127,"endTime":0,"childRecords":[],"interuppted":false},{"testStatus":{"stackTrace":"","statusValue":"PASSED"},"type":"MESSAGE","name":"","message":"Text of object \u0027Object Repository/Page_BugsUI Edit Product/unkown_defaultAssignee\u0027 is cleared","startTime":1556620169180,"endTime":0,"childRecords":[],"interuppted":false},{"testStatus":{"stackTrace":"","statusValue":"PASSED"},"type":"MESSAGE","name":"","message":"Text \u0027kumar.nagendra@happiestminds.com\u0027 is set on object \u0027Object Repository/Page_BugsUI Edit Product/unkown_defaultAssignee\u0027","startTime":1556620169626,"endTime":0,"childRecords":[],"interuppted":false},{"testStatus":{"stackTrace":"","statusValue":"PASSED"},"type":"MESSAGE","name":"","message":"Object: \u0027Object Repository/Page_BugsUI Edit Product/update_icon_unknownComponent\u0027 is clicked on","startTime":1556620169708,"endTime":0,"childRecords":[],"interuppted":false},{"testStatus":{"stackTrace":"","statusValue":"PASSED"},"type":"MESSAGE","name":"","message":"Delayed 2 second(s)","startTime":1556620171709,"endTime":0,"childRecords":[],"interuppted":false},{"testStatus":{"stackTrace":"","statusValue":"PASSED"},"type":"MESSAGE","name":"","message":"reusable.editPage.resetUnkownComponent is PASSED","startTime":1556620171709,"endTime":0,"childRecords":[],"interuppted":false}],"interuppted":false},{"index":16,"isIgnoredIfFailed":false,"type":"TEST_STEP","name":"delay","message":"Delayed 3 second(s)","description":"","startTime":1556620171709,"endTime":1556620174711,"childRecords":[{"testStatus":{"stackTrace":"","statusValue":"PASSED"},"type":"MESSAGE","name":"","message":"Delayed 3 second(s)","startTime":1556620174711,"endTime":0,"childRecords":[],"interuppted":false}],"interuppted":false},{"testStatus":{"stackTrace":"","statusValue":"PASSED"},"type":"MESSAGE","name":"","message":"Test Cases/Edit_Product/default_UnknownComponent","startTime":1556620174711,"endTime":0,"childRecords":[],"interuppted":false}],"interuppted":false},{"isOptional":false,"type":"TEST_CASE","name":"Test Cases/Edit_Product/component_section","id":"Test Cases/Edit_Product/component_section","source":"C:\\\\New-Bugzilla-Application\\\\New_Bugzilla-UI-V2\\\\Test Cases\\\\Edit_Product\\\\component_section.tc","message":"Test Cases/Edit_Product/component_section","description":"","startTime":1556620174717,"endTime":1556620190006,"childRecords":[{"testStatus":{"stackTrace":"","statusValue":"INFO"},"type":"MESSAGE","name":"","message":"Evaluating variables for test case","startTime":1556620174741,"endTime":0,"childRecords":[],"interuppted":false},{"index":1,"isIgnoredIfFailed":false,"type":"TEST_STEP","name":"Statement - If (com.kms.katalon.core.webui.keyword.WebUiBuiltInKeywords.verifyElementPresent(com.kms.katalon.core.testobject.ObjectRepository.findTestObject(Page_BugsUI Edit Product/button_AddNewRow_Component), 0))","message":"Object: \u0027Object Repository/Page_BugsUI Edit Product/button_AddNewRow_Component\u0027 is clicked on","description":"","startTime":1556620175028,"endTime":1556620175220,"childRecords":[{"testStatus":{"stackTrace":"","statusValue":"WARNING"},"type":"MESSAGE","name":"","message":"Timeout \u00270\u0027 is invalid. Using default page load timeout: \u002730\u0027","startTime":1556620175033,"endTime":0,"childRecords":[],"interuppted":false},{"testStatus":{"stackTrace":"","statusValue":"PASSED"},"type":"MESSAGE","name":"","message":"Object \u0027Object Repository/Page_BugsUI Edit Product/button_AddNewRow_Component\u0027 is present","startTime":1556620175071,"endTime":0,"childRecords":[],"interuppted":false},{"index":1,"isIgnoredIfFailed":false,"type":"TEST_STEP","name":"click","message":"Object: \u0027Object Repository/Page_BugsUI Edit Product/button_AddNewRow_Component\u0027 is clicked on","description":"","startTime":1556620175071,"endTime":1556620175219,"childRecords":[{"testStatus":{"stackTrace":"","statusValue":"PASSED"},"type":"MESSAGE","name":"","message":"Object: \u0027Object Repository/Page_BugsUI Edit Product/button_AddNewRow_Component\u0027 is clicked on","startTime":1556620175219,"endTime":0,"childRecords":[],"interuppted":false}],"interuppted":false}],"interuppted":false},{"index":2,"isIgnoredIfFailed":false,"type":"TEST_STEP","name":"setText","message":"Text \u0027C1 description\u0027 is set on object \u0027Object Repository/Page_BugsUI Edit Product/unkown_description\u0027","description":"","startTime":1556620175220,"endTime":1556620175489,"childRecords":[{"testStatus":{"stackTrace":"","statusValue":"PASSED"},"type":"MESSAGE","name":"","message":"Text \u0027C1 description\u0027 is set on object \u0027Object Repository/Page_BugsUI Edit Product/unkown_description\u0027","startTime":1556620175489,"endTime":0,"childRecords":[],"interuppted":false}],"interuppted":false},{"index":3,"isIgnoredIfFailed":false,"type":"TEST_STEP","name":"Statement - If (com.kms.katalon.core.webui.keyword.WebUiBuiltInKeywords.verifyElementPresent(com.kms.katalon.core.testobject.ObjectRepository.findTestObject(Page_BugsUI Edit Product/button_Add_component), 0))","message":"Object: \u0027Object Repository/Page_BugsUI Edit Product/button_Add_component\u0027 is clicked on","description":"","startTime":1556620175489,"endTime":1556620175625,"childRecords":[{"testStatus":{"stackTrace":"","statusValue":"WARNING"},"type":"MESSAGE","name":"","message":"Timeout \u00270\u0027 is invalid. Using default page load timeout: \u002730\u0027","startTime":1556620175495,"endTime":0,"childRecords":[],"interuppted":false},{"testStatus":{"stackTrace":"","statusValue":"PASSED"},"type":"MESSAGE","name":"","message":"Object \u0027Object Repository/Page_BugsUI Edit Product/button_Add_component\u0027 is present","startTime":1556620175521,"endTime":0,"childRecords":[],"interuppted":false},{"index":1,"isIgnoredIfFailed":false,"type":"TEST_STEP","name":"click","message":"Object: \u0027Object Repository/Page_BugsUI Edit Product/button_Add_component\u0027 is clicked on","description":"","startTime":1556620175522,"endTime":1556620175624,"childRecords":[{"testStatus":{"stackTrace":"","statusValue":"PASSED"},"type":"MESSAGE","name":"","message":"Object: \u0027Object Repository/Page_BugsUI Edit Product/button_Add_component\u0027 is clicked on","startTime":1556620175624,"endTime":0,"childRecords":[],"interuppted":false}],"interuppted":false}],"interuppted":false},{"index":4,"isIgnoredIfFailed":false,"type":"TEST_STEP","name":"Statement - If (com.kms.katalon.core.webui.keyword.WebUiBuiltInKeywords.verifyElementPresent(com.kms.katalon.core.testobject.ObjectRepository.findTestObject(Page_BugsUI Edit Product/div_Name_Email_required), 0))","description":"","startTime":1556620175625,"endTime":1556620176740,"childRecords":[{"testStatus":{"stackTrace":"","statusValue":"WARNING"},"type":"MESSAGE","name":"","message":"Timeout \u00270\u0027 is invalid. Using default page load timeout: \u002730\u0027","startTime":1556620175630,"endTime":0,"childRecords":[],"interuppted":false},{"testStatus":{"stackTrace":"","statusValue":"PASSED"},"type":"MESSAGE","name":"","message":"Object \u0027Object Repository/Page_BugsUI Edit Product/div_Name_Email_required\u0027 is present","startTime":1556620176695,"endTime":0,"childRecords":[],"interuppted":false},{"index":1,"isIgnoredIfFailed":false,"type":"TEST_STEP","name":"Statement - componentNameEmailReqMsg \u003d com.kms.katalon.core.webui.keyword.WebUiBuiltInKeywords.getText(com.kms.katalon.core.testobject.ObjectRepository.findTestObject(Page_BugsUI Edit Product/div_Name_Email_required))","message":"Text of object \u0027Object Repository/Page_BugsUI Edit Product/div_Name_Email_required\u0027 is: \u0027Name is required, Email is required\u0027","description":"","startTime":1556620176696,"endTime":1556620176738,"childRecords":[{"testStatus":{"stackTrace":"","statusValue":"PASSED"},"type":"MESSAGE","name":"","message":"Text of object \u0027Object Repository/Page_BugsUI Edit Product/div_Name_Email_required\u0027 is: \u0027Name is required, Email is required\u0027","startTime":1556620176738,"endTime":0,"childRecords":[],"interuppted":false}],"interuppted":false},{"index":2,"isIgnoredIfFailed":false,"type":"TEST_STEP","name":"Statement - If (componentNameEmailReqMsg.equals(\"Name is required, Email is required\"))","description":"","startTime":1556620176738,"endTime":1556620176739,"childRecords":[{"index":1,"isIgnoredIfFailed":false,"type":"TEST_STEP","name":"Statement - assert true","description":"","startTime":1556620176739,"endTime":1556620176739,"childRecords":[],"interuppted":false}],"interuppted":false}],"interuppted":false},{"index":5,"isIgnoredIfFailed":false,"type":"TEST_STEP","name":"delay","message":"Delayed 2 second(s)","description":"","startTime":1556620176740,"endTime":1556620178740,"childRecords":[{"testStatus":{"stackTrace":"","statusValue":"PASSED"},"type":"MESSAGE","name":"","message":"Delayed 2 second(s)","startTime":1556620178740,"endTime":0,"childRecords":[],"interuppted":false}],"interuppted":false},{"index":6,"isIgnoredIfFailed":false,"type":"TEST_STEP","name":"setText","message":"Text \u0027C1\u0027 is set on object \u0027Object Repository/Page_BugsUI Edit Product/unknown_Component\u0027","description":"","startTime":1556620178741,"endTime":1556620178916,"childRecords":[{"testStatus":{"stackTrace":"","statusValue":"PASSED"},"type":"MESSAGE","name":"","message":"Text \u0027C1\u0027 is set on object \u0027Object Repository/Page_BugsUI Edit Product/unknown_Component\u0027","startTime":1556620178915,"endTime":0,"childRecords":[],"interuppted":false}],"interuppted":false},{"index":7,"isIgnoredIfFailed":false,"type":"TEST_STEP","name":"setText","message":"Text \u0027kumar.nagendra@happiestminds.com\u0027 is set on object \u0027Object Repository/Page_BugsUI Edit Product/unkown_defaultAssignee\u0027","description":"","startTime":1556620178916,"endTime":1556620179343,"childRecords":[{"testStatus":{"stackTrace":"","statusValue":"PASSED"},"type":"MESSAGE","name":"","message":"Text \u0027kumar.nagendra@happiestminds.com\u0027 is set on object \u0027Object Repository/Page_BugsUI Edit Product/unkown_defaultAssignee\u0027","startTime":1556620179343,"endTime":0,"childRecords":[],"interuppted":false}],"interuppted":false},{"index":8,"isIgnoredIfFailed":false,"type":"TEST_STEP","name":"Statement - If (com.kms.katalon.core.webui.keyword.WebUiBuiltInKeywords.verifyElementPresent(com.kms.katalon.core.testobject.ObjectRepository.findTestObject(Page_BugsUI Edit Product/button_Add_component), 0))","message":"Object: \u0027Object Repository/Page_BugsUI Edit Product/button_Add_component\u0027 is clicked on","description":"","startTime":1556620179343,"endTime":1556620179450,"childRecords":[{"testStatus":{"stackTrace":"","statusValue":"WARNING"},"type":"MESSAGE","name":"","message":"Timeout \u00270\u0027 is invalid. Using default page load timeout: \u002730\u0027","startTime":1556620179350,"endTime":0,"childRecords":[],"interuppted":false},{"testStatus":{"stackTrace":"","statusValue":"PASSED"},"type":"MESSAGE","name":"","message":"Object \u0027Object Repository/Page_BugsUI Edit Product/button_Add_component\u0027 is present","startTime":1556620179363,"endTime":0,"childRecords":[],"interuppted":false},{"index":1,"isIgnoredIfFailed":false,"type":"TEST_STEP","name":"click","message":"Object: \u0027Object Repository/Page_BugsUI Edit Product/button_Add_component\u0027 is clicked on","description":"","startTime":1556620179363,"endTime":1556620179448,"childRecords":[{"testStatus":{"stackTrace":"","statusValue":"PASSED"},"type":"MESSAGE","name":"","message":"Object: \u0027Object Repository/Page_BugsUI Edit Product/button_Add_component\u0027 is clicked on","startTime":1556620179447,"endTime":0,"childRecords":[],"interuppted":false}],"interuppted":false}],"interuppted":false},{"index":9,"isIgnoredIfFailed":false,"type":"TEST_STEP","name":"Statement - If (com.kms.katalon.core.webui.keyword.WebUiBuiltInKeywords.verifyElementPresent(com.kms.katalon.core.testobject.ObjectRepository.findTestObject(Page_BugsUI Edit Product/div_Component_added), 0))","description":"","startTime":1556620179450,"endTime":1556620180088,"childRecords":[{"testStatus":{"stackTrace":"","statusValue":"WARNING"},"type":"MESSAGE","name":"","message":"Timeout \u00270\u0027 is invalid. Using default page load timeout: \u002730\u0027","startTime":1556620179456,"endTime":0,"childRecords":[],"interuppted":false},{"testStatus":{"stackTrace":"","statusValue":"PASSED"},"type":"MESSAGE","name":"","message":"Object \u0027Object Repository/Page_BugsUI Edit Product/div_Component_added\u0027 is present","startTime":1556620179996,"endTime":0,"childRecords":[],"interuppted":false},{"index":1,"isIgnoredIfFailed":false,"type":"TEST_STEP","name":"Statement - componentAddedSuccessMsg \u003d com.kms.katalon.core.webui.keyword.WebUiBuiltInKeywords.getText(com.kms.katalon.core.testobject.ObjectRepository.findTestObject(Page_BugsUI Edit Product/div_Component_added))","message":"Text of object \u0027Object Repository/Page_BugsUI Edit Product/div_Component_added\u0027 is: \u0027Component has been added successfully.\u0027","description":"","startTime":1556620179996,"endTime":1556620180087,"childRecords":[{"testStatus":{"stackTrace":"","statusValue":"PASSED"},"type":"MESSAGE","name":"","message":"Text of object \u0027Object Repository/Page_BugsUI Edit Product/div_Component_added\u0027 is: \u0027Component has been added successfully.\u0027","startTime":1556620180086,"endTime":0,"childRecords":[],"interuppted":false}],"interuppted":false},{"index":2,"isIgnoredIfFailed":false,"type":"TEST_STEP","name":"Statement - If (componentAddedSuccessMsg.equals(\"Component has been added successfully.\"))","description":"","startTime":1556620180087,"endTime":1556620180088,"childRecords":[{"index":1,"isIgnoredIfFailed":false,"type":"TEST_STEP","name":"Statement - assert true","description":"","startTime":1556620180087,"endTime":1556620180088,"childRecords":[],"interuppted":false}],"interuppted":false}],"interuppted":false},{"index":10,"isIgnoredIfFailed":false,"type":"TEST_STEP","name":"delay","message":"Delayed 3 second(s)","description":"","startTime":1556620180088,"endTime":1556620183091,"childRecords":[{"testStatus":{"stackTrace":"","statusValue":"PASSED"},"type":"MESSAGE","name":"","message":"Delayed 3 second(s)","startTime":1556620183090,"endTime":0,"childRecords":[],"interuppted":false}],"interuppted":false},{"index":11,"isIgnoredIfFailed":false,"type":"TEST_STEP","name":"Statement - compName \u003d com.kms.katalon.core.webui.keyword.WebUiBuiltInKeywords.getAttribute(com.kms.katalon.core.testobject.ObjectRepository.findTestObject(Page_BugsUI Edit Product/unknown_Component), \"value\")","message":"Attribute \u0027value\u0027 of object \u0027Object Repository/Page_BugsUI Edit Product/unknown_Component\u0027 is: \u0027C1\u0027","description":"","startTime":1556620183091,"endTime":1556620183125,"childRecords":[{"testStatus":{"stackTrace":"","statusValue":"PASSED"},"type":"MESSAGE","name":"","message":"Attribute \u0027value\u0027 of object \u0027Object Repository/Page_BugsUI Edit Product/unknown_Component\u0027 is: \u0027C1\u0027","startTime":1556620183125,"endTime":0,"childRecords":[],"interuppted":false}],"interuppted":false},{"index":12,"isIgnoredIfFailed":false,"type":"TEST_STEP","name":"Statement - If (compName.equals(\"C1\"))","description":"","startTime":1556620183125,"endTime":1556620183126,"childRecords":[{"index":1,"isIgnoredIfFailed":false,"type":"TEST_STEP","name":"Statement - assert true","description":"","startTime":1556620183126,"endTime":1556620183126,"childRecords":[],"interuppted":false}],"interuppted":false},{"index":14,"isIgnoredIfFailed":false,"type":"TEST_STEP","name":"delay","message":"Delayed 3 second(s)","description":"","startTime":1556620183126,"endTime":1556620186128,"childRecords":[{"testStatus":{"stackTrace":"","statusValue":"PASSED"},"type":"MESSAGE","name":"","message":"Delayed 3 second(s)","startTime":1556620186128,"endTime":0,"childRecords":[],"interuppted":false}],"interuppted":false},{"index":15,"isIgnoredIfFailed":false,"type":"TEST_STEP","name":"Statement - If (com.kms.katalon.core.webui.keyword.WebUiBuiltInKeywords.verifyElementPresent(com.kms.katalon.core.testobject.ObjectRepository.findTestObject(Page_BugsUI Edit Product/delete_icon_unknownCompnent), 0))","message":"Object: \u0027Object Repository/Page_BugsUI Edit Product/delete_icon_unknownCompnent\u0027 is clicked on","description":"","startTime":1556620186128,"endTime":1556620186261,"childRecords":[{"testStatus":{"stackTrace":"","statusValue":"WARNING"},"type":"MESSAGE","name":"","message":"Timeout \u00270\u0027 is invalid. Using default page load timeout: \u002730\u0027","startTime":1556620186133,"endTime":0,"childRecords":[],"interuppted":false},{"testStatus":{"stackTrace":"","statusValue":"PASSED"},"type":"MESSAGE","name":"","message":"Object \u0027Object Repository/Page_BugsUI Edit Product/delete_icon_unknownCompnent\u0027 is present","startTime":1556620186161,"endTime":0,"childRecords":[],"interuppted":false},{"index":1,"isIgnoredIfFailed":false,"type":"TEST_STEP","name":"click","message":"Object: \u0027Object Repository/Page_BugsUI Edit Product/delete_icon_unknownCompnent\u0027 is clicked on","description":"","startTime":1556620186161,"endTime":1556620186261,"childRecords":[{"testStatus":{"stackTrace":"","statusValue":"PASSED"},"type":"MESSAGE","name":"","message":"Object: \u0027Object Repository/Page_BugsUI Edit Product/delete_icon_unknownCompnent\u0027 is clicked on","startTime":1556620186260,"endTime":0,"childRecords":[],"interuppted":false}],"interuppted":false}],"interuppted":false},{"index":16,"isIgnoredIfFailed":false,"type":"TEST_STEP","name":"reusable.editPage.deleteComponent","message":"reusable.editPage.deleteComponent is PASSED","description":"","startTime":1556620186261,"endTime":1556620186486,"childRecords":[{"testStatus":{"stackTrace":"","statusValue":"WARNING"},"type":"MESSAGE","name":"","message":"Timeout \u00270\u0027 is invalid. Using default page load timeout: \u002730\u0027","startTime":1556620186267,"endTime":0,"childRecords":[],"interuppted":false},{"testStatus":{"stackTrace":"","statusValue":"PASSED"},"type":"MESSAGE","name":"","message":"Object \u0027Object Repository/Page_BugsUI Edit Product/confirmDeleteProduct_popup\u0027 is present","startTime":1556620186325,"endTime":0,"childRecords":[],"interuppted":false},{"testStatus":{"stackTrace":"","statusValue":"WARNING"},"type":"MESSAGE","name":"","message":"Timeout \u00270\u0027 is invalid. Using default page load timeout: \u002730\u0027","startTime":1556620186329,"endTime":0,"childRecords":[],"interuppted":false},{"testStatus":{"stackTrace":"","statusValue":"PASSED"},"type":"MESSAGE","name":"","message":"Object \u0027Object Repository/Page_BugsUI Edit Product/button_component_Yes\u0027 is present","startTime":1556620186352,"endTime":0,"childRecords":[],"interuppted":false},{"testStatus":{"stackTrace":"","statusValue":"PASSED"},"type":"MESSAGE","name":"","message":"Object: \u0027Object Repository/Page_BugsUI Edit Product/button_component_Yes\u0027 is clicked on","startTime":1556620186485,"endTime":0,"childRecords":[],"interuppted":false},{"testStatus":{"stackTrace":"","statusValue":"PASSED"},"type":"MESSAGE","name":"","message":"reusable.editPage.deleteComponent is PASSED","startTime":1556620186486,"endTime":0,"childRecords":[],"interuppted":false}],"interuppted":false},{"index":17,"isIgnoredIfFailed":false,"type":"TEST_STEP","name":"Statement - If (com.kms.katalon.core.webui.keyword.WebUiBuiltInKeywords.verifyElementPresent(com.kms.katalon.core.testobject.ObjectRepository.findTestObject(Page_BugsUI Edit Product/div_Component_deleted), 0))","description":"","startTime":1556620186486,"endTime":1556620187107,"childRecords":[{"testStatus":{"stackTrace":"","statusValue":"WARNING"},"type":"MESSAGE","name":"","message":"Timeout \u00270\u0027 is invalid. Using default page load timeout: \u002730\u0027","startTime":1556620186491,"endTime":0,"childRecords":[],"interuppted":false},{"testStatus":{"stackTrace":"","statusValue":"PASSED"},"type":"MESSAGE","name":"","message":"Object \u0027Object Repository/Page_BugsUI Edit Product/div_Component_deleted\u0027 is present","startTime":1556620187047,"endTime":0,"childRecords":[],"interuppted":false},{"index":1,"isIgnoredIfFailed":false,"type":"TEST_STEP","name":"Statement - componentDeletedSuccessMsg \u003d com.kms.katalon.core.webui.keyword.WebUiBuiltInKeywords.getText(com.kms.katalon.core.testobject.ObjectRepository.findTestObject(Page_BugsUI Edit Product/div_Component_deleted))","message":"Text of object \u0027Object Repository/Page_BugsUI Edit Product/div_Component_deleted\u0027 is: \u0027Component has been deleted successfully.\u0027","description":"","startTime":1556620187049,"endTime":1556620187105,"childRecords":[{"testStatus":{"stackTrace":"","statusValue":"PASSED"},"type":"MESSAGE","name":"","message":"Text of object \u0027Object Repository/Page_BugsUI Edit Product/div_Component_deleted\u0027 is: \u0027Component has been deleted successfully.\u0027","startTime":1556620187105,"endTime":0,"childRecords":[],"interuppted":false}],"interuppted":false},{"index":2,"isIgnoredIfFailed":false,"type":"TEST_STEP","name":"Statement - If (componentDeletedSuccessMsg.equals(\"Component has been deleted successfully.\"))","description":"","startTime":1556620187106,"endTime":1556620187107,"childRecords":[{"index":1,"isIgnoredIfFailed":false,"type":"TEST_STEP","name":"Statement - assert true","description":"","startTime":1556620187106,"endTime":1556620187107,"childRecords":[],"interuppted":false}],"interuppted":false}],"interuppted":false},{"index":18,"isIgnoredIfFailed":false,"type":"TEST_STEP","name":"delay","message":"Delayed 2 second(s)","description":"","startTime":1556620187107,"endTime":1556620189108,"childRecords":[{"testStatus":{"stackTrace":"","statusValue":"PASSED"},"type":"MESSAGE","name":"","message":"Delayed 2 second(s)","startTime":1556620189108,"endTime":0,"childRecords":[],"interuppted":false}],"interuppted":false},{"index":19,"isIgnoredIfFailed":false,"type":"TEST_STEP","name":"Statement - If (!(com.kms.katalon.core.webui.keyword.WebUiBuiltInKeywords.getAttribute(com.kms.katalon.core.testobject.ObjectRepository.findTestObject(Page_BugsUI Edit Product/unknown_Component), \"value\").equals(\"C1\")))","description":"","startTime":1556620189108,"endTime":1556620189136,"childRecords":[{"testStatus":{"stackTrace":"","statusValue":"PASSED"},"type":"MESSAGE","name":"","message":"Attribute \u0027value\u0027 of object \u0027Object Repository/Page_BugsUI Edit Product/unknown_Component\u0027 is: \u0027Unknown\u0027","startTime":1556620189135,"endTime":0,"childRecords":[],"interuppted":false},{"index":1,"isIgnoredIfFailed":false,"type":"TEST_STEP","name":"Statement - assert true","description":"","startTime":1556620189135,"endTime":1556620189136,"childRecords":[],"interuppted":false}],"interuppted":false},{"index":21,"isIgnoredIfFailed":false,"type":"TEST_STEP","name":"closeBrowser","message":"Browser is closed","description":"","startTime":1556620189137,"endTime":1556620190006,"childRecords":[{"testStatus":{"stackTrace":"","statusValue":"PASSED"},"type":"MESSAGE","name":"","message":"Browser is closed","startTime":1556620190005,"endTime":0,"childRecords":[],"interuppted":false}],"interuppted":false},{"testStatus":{"stackTrace":"","statusValue":"PASSED"},"type":"MESSAGE","name":"","message":"Test Cases/Edit_Product/component_section","startTime":1556620190006,"endTime":0,"childRecords":[],"interuppted":false}],"interuppted":false}],"interuppted":false}